{
"meta":{"test_sets":[],"test_metrics":[],"learn_metrics":[{"best_value":"Min","name":"RMSE"}],"launch_mode":"Train","parameters":"","iteration_count":1000,"learn_sets":["learn"],"name":"experiment"},
"iterations":[
{"learn":[14.48084543],"iteration":0,"passed_time":0.002165324379,"remaining_time":2.163159055},
{"learn":[14.1310727],"iteration":1,"passed_time":0.004137967742,"remaining_time":2.064845903},
{"learn":[13.79658352],"iteration":2,"passed_time":0.005700252893,"remaining_time":1.894384045},
{"learn":[13.4565295],"iteration":3,"passed_time":0.007211662142,"remaining_time":1.795703873},
{"learn":[13.13597033],"iteration":4,"passed_time":0.01001612939,"remaining_time":1.993209749},
{"learn":[12.86588984],"iteration":5,"passed_time":0.01252504404,"remaining_time":2.074982297},
{"learn":[12.56779054],"iteration":6,"passed_time":0.01400069588,"remaining_time":1.986098716},
{"learn":[12.30450423],"iteration":7,"passed_time":0.01542588555,"remaining_time":1.912809808},
{"learn":[12.05370259],"iteration":8,"passed_time":0.01688469563,"remaining_time":1.859192596},
{"learn":[11.76649097],"iteration":9,"passed_time":0.01834281324,"remaining_time":1.815938511},
{"learn":[11.47626471],"iteration":10,"passed_time":0.02028492554,"remaining_time":1.823799214},
{"learn":[11.235871],"iteration":11,"passed_time":0.02172273557,"remaining_time":1.788505228},
{"learn":[11.03147178],"iteration":12,"passed_time":0.02545131718,"remaining_time":1.932342312},
{"learn":[10.80226152],"iteration":13,"passed_time":0.02722010456,"remaining_time":1.917073079},
{"learn":[10.57382116],"iteration":14,"passed_time":0.02893078463,"remaining_time":1.899788191},
{"learn":[10.33725052],"iteration":15,"passed_time":0.03057853291,"remaining_time":1.880579774},
{"learn":[10.13149907],"iteration":16,"passed_time":0.03243707233,"remaining_time":1.875626006},
{"learn":[9.924342123],"iteration":17,"passed_time":0.0340382897,"remaining_time":1.856977805},
{"learn":[9.723539884],"iteration":18,"passed_time":0.03547967074,"remaining_time":1.831871421},
{"learn":[9.536481381],"iteration":19,"passed_time":0.03688332742,"remaining_time":1.807283043},
{"learn":[9.365078282],"iteration":20,"passed_time":0.03977134783,"remaining_time":1.854102358},
{"learn":[9.202560509],"iteration":21,"passed_time":0.04138774681,"remaining_time":1.839873472},
{"learn":[9.032825497],"iteration":22,"passed_time":0.0427914964,"remaining_time":1.817708347},
{"learn":[8.860037097],"iteration":23,"passed_time":0.0442310034,"remaining_time":1.798727472},
{"learn":[8.712078217],"iteration":24,"passed_time":0.04568038371,"remaining_time":1.781534965},
{"learn":[8.565016942],"iteration":25,"passed_time":0.04710454081,"remaining_time":1.764608567},
{"learn":[8.424428152],"iteration":26,"passed_time":0.04860557713,"remaining_time":1.751600983},
{"learn":[8.299069426],"iteration":27,"passed_time":0.05025220477,"remaining_time":1.744469394},
{"learn":[8.165727743],"iteration":28,"passed_time":0.05169111572,"remaining_time":1.730761151},
{"learn":[8.04087074],"iteration":29,"passed_time":0.05455065661,"remaining_time":1.763804564},
{"learn":[7.924413875],"iteration":30,"passed_time":0.05606234109,"remaining_time":1.752400275},
{"learn":[7.8004774],"iteration":31,"passed_time":0.05753419753,"remaining_time":1.740409475},
{"learn":[7.701865422],"iteration":32,"passed_time":0.05894799923,"remaining_time":1.727355008},
{"learn":[7.587826214],"iteration":33,"passed_time":0.06039550901,"remaining_time":1.715942991},
{"learn":[7.481218613],"iteration":34,"passed_time":0.06188771511,"remaining_time":1.706332717},
{"learn":[7.388796733],"iteration":35,"passed_time":0.06329723056,"remaining_time":1.694959174},
{"learn":[7.295738785],"iteration":36,"passed_time":0.06499954934,"remaining_time":1.691745028},
{"learn":[7.228243196],"iteration":37,"passed_time":0.06666892966,"remaining_time":1.687776588},
{"learn":[7.143527694],"iteration":38,"passed_time":0.0706154019,"remaining_time":1.740035929},
{"learn":[7.066648497],"iteration":39,"passed_time":0.07214614052,"remaining_time":1.731507373},
{"learn":[6.987956751],"iteration":40,"passed_time":0.07357816717,"remaining_time":1.721011276},
{"learn":[6.924907881],"iteration":41,"passed_time":0.07517773665,"remaining_time":1.714768374},
{"learn":[6.848903517],"iteration":42,"passed_time":0.07664895322,"remaining_time":1.705884843},
{"learn":[6.787640286],"iteration":43,"passed_time":0.07829903879,"remaining_time":1.70122457},
{"learn":[6.713765943],"iteration":44,"passed_time":0.07982206214,"remaining_time":1.694001541},
{"learn":[6.64337757],"iteration":45,"passed_time":0.08126640236,"remaining_time":1.685394519},
{"learn":[6.580440486],"iteration":46,"passed_time":0.0840041306,"remaining_time":1.703317797},
{"learn":[6.523725288],"iteration":47,"passed_time":0.08580061389,"remaining_time":1.701712176},
{"learn":[6.463713508],"iteration":48,"passed_time":0.0873549103,"remaining_time":1.695398361},
{"learn":[6.411149311],"iteration":49,"passed_time":0.08894512714,"remaining_time":1.689957416},
{"learn":[6.357210789],"iteration":50,"passed_time":0.0903956522,"remaining_time":1.682068116},
{"learn":[6.303760517],"iteration":51,"passed_time":0.09182096809,"remaining_time":1.67396688},
{"learn":[6.254060538],"iteration":52,"passed_time":0.09329359062,"remaining_time":1.666962836},
{"learn":[6.208061787],"iteration":53,"passed_time":0.0947686955,"remaining_time":1.660207147},
{"learn":[6.168462083],"iteration":54,"passed_time":0.09627717537,"remaining_time":1.654216922},
{"learn":[6.129334835],"iteration":55,"passed_time":0.09922938802,"remaining_time":1.672723969},
{"learn":[6.088151548],"iteration":56,"passed_time":0.1013133672,"remaining_time":1.676114128},
{"learn":[6.049974754],"iteration":57,"passed_time":0.1030259345,"remaining_time":1.673283281},
{"learn":[6.014126503],"iteration":58,"passed_time":0.10456263,"remaining_time":1.667685337},
{"learn":[5.982835603],"iteration":59,"passed_time":0.106080033,"remaining_time":1.661920518},
{"learn":[5.94768361],"iteration":60,"passed_time":0.1075525293,"remaining_time":1.655603689},
{"learn":[5.916260224],"iteration":61,"passed_time":0.1089756784,"remaining_time":1.648696554},
{"learn":[5.88693351],"iteration":62,"passed_time":0.1104056943,"remaining_time":1.642065644},
{"learn":[5.855166915],"iteration":63,"passed_time":0.1118749176,"remaining_time":1.63617067},
{"learn":[5.829874582],"iteration":64,"passed_time":0.1154122443,"remaining_time":1.660160746},
{"learn":[5.798657545],"iteration":65,"passed_time":0.1169229015,"remaining_time":1.654636212},
{"learn":[5.769192952],"iteration":66,"passed_time":0.1183965882,"remaining_time":1.648716668},
{"learn":[5.743145884],"iteration":67,"passed_time":0.1199486915,"remaining_time":1.644002654},
{"learn":[5.718714209],"iteration":68,"passed_time":0.1215593737,"remaining_time":1.64017068},
{"learn":[5.698139743],"iteration":69,"passed_time":0.1227216429,"remaining_time":1.630444684},
{"learn":[5.677471823],"iteration":70,"passed_time":0.1241474549,"remaining_time":1.624408248},
{"learn":[5.655034423],"iteration":71,"passed_time":0.1255242002,"remaining_time":1.617867469},
{"learn":[5.632157491],"iteration":72,"passed_time":0.1271327405,"remaining_time":1.614411651},
{"learn":[5.609996178],"iteration":73,"passed_time":0.1298981095,"remaining_time":1.625481748},
{"learn":[5.593306513],"iteration":74,"passed_time":0.1318876143,"remaining_time":1.62661391},
{"learn":[5.576507853],"iteration":75,"passed_time":0.1334831149,"remaining_time":1.62287366},
{"learn":[5.558469211],"iteration":76,"passed_time":0.1351222372,"remaining_time":1.619712012},
{"learn":[5.540380059],"iteration":77,"passed_time":0.1368284987,"remaining_time":1.617383023},
{"learn":[5.525117151],"iteration":78,"passed_time":0.1387160944,"remaining_time":1.617183834},
{"learn":[5.510804282],"iteration":79,"passed_time":0.1402164102,"remaining_time":1.612488717},
{"learn":[5.494647869],"iteration":80,"passed_time":0.1416318878,"remaining_time":1.606909937},
{"learn":[5.477170541],"iteration":81,"passed_time":0.1444649152,"remaining_time":1.617302344},
{"learn":[5.462097874],"iteration":82,"passed_time":0.1462049019,"remaining_time":1.61529994},
{"learn":[5.445766738],"iteration":83,"passed_time":0.1477109818,"remaining_time":1.610753087},
{"learn":[5.428431647],"iteration":84,"passed_time":0.1491338013,"remaining_time":1.605381508},
{"learn":[5.41506457],"iteration":85,"passed_time":0.1505924185,"remaining_time":1.600482215},
{"learn":[5.401414363],"iteration":86,"passed_time":0.1526214337,"remaining_time":1.601647919},
{"learn":[5.389692775],"iteration":87,"passed_time":0.1540529537,"remaining_time":1.596548793},
{"learn":[5.379931015],"iteration":88,"passed_time":0.1552169286,"remaining_time":1.588793505},
{"learn":[5.363522967],"iteration":89,"passed_time":0.1567743945,"remaining_time":1.585163323},
{"learn":[5.350848239],"iteration":90,"passed_time":0.1595499133,"remaining_time":1.593745837},
{"learn":[5.341686645],"iteration":91,"passed_time":0.1611843707,"remaining_time":1.590819659},
{"learn":[5.332823512],"iteration":92,"passed_time":0.1626482314,"remaining_time":1.586257482},
{"learn":[5.321385599],"iteration":93,"passed_time":0.1641511014,"remaining_time":1.582137211},
{"learn":[5.312977009],"iteration":94,"passed_time":0.1660036729,"remaining_time":1.58140341},
{"learn":[5.305117904],"iteration":95,"passed_time":0.1675458275,"remaining_time":1.577723209},
{"learn":[5.298334609],"iteration":96,"passed_time":0.16850852,"remaining_time":1.568692717},
{"learn":[5.290345316],"iteration":97,"passed_time":0.1694608886,"remaining_time":1.559731852},
{"learn":[5.275671372],"iteration":98,"passed_time":0.1709100638,"remaining_time":1.555454217},
{"learn":[5.2611511],"iteration":99,"passed_time":0.1725722351,"remaining_time":1.553150116},
{"learn":[5.249375941],"iteration":100,"passed_time":0.1750169386,"remaining_time":1.557824038},
{"learn":[5.237275991],"iteration":101,"passed_time":0.1765279622,"remaining_time":1.554138334},
{"learn":[5.227994847],"iteration":102,"passed_time":0.1780035282,"remaining_time":1.550186066},
{"learn":[5.218484758],"iteration":103,"passed_time":0.1795790551,"remaining_time":1.547142629},
{"learn":[5.213026968],"iteration":104,"passed_time":0.1805908967,"remaining_time":1.539322405},
{"learn":[5.203822525],"iteration":105,"passed_time":0.1820306264,"remaining_time":1.535239434},
{"learn":[5.19327854],"iteration":106,"passed_time":0.183459913,"remaining_time":1.531118713},
{"learn":[5.183169477],"iteration":107,"passed_time":0.1849375458,"remaining_time":1.527447137},
{"learn":[5.17500222],"iteration":108,"passed_time":0.1864542002,"remaining_time":1.524134793},
{"learn":[5.166729589],"iteration":109,"passed_time":0.1894141391,"remaining_time":1.53253258},
{"learn":[5.159380729],"iteration":110,"passed_time":0.191072724,"remaining_time":1.530303168},
{"learn":[5.152910737],"iteration":111,"passed_time":0.1926056241,"remaining_time":1.527087449},
{"learn":[5.146091609],"iteration":112,"passed_time":0.1942010353,"remaining_time":1.524392198},
{"learn":[5.14093281],"iteration":113,"passed_time":0.1956359738,"remaining_time":1.52046906},
{"learn":[5.134356134],"iteration":114,"passed_time":0.1971399045,"remaining_time":1.517120135},
{"learn":[5.128807661],"iteration":115,"passed_time":0.1985762051,"remaining_time":1.513287632},
{"learn":[5.121681927],"iteration":116,"passed_time":0.1999917652,"remaining_time":1.509339561},
{"learn":[5.114685243],"iteration":117,"passed_time":0.201520465,"remaining_time":1.506280086},
{"learn":[5.105157235],"iteration":118,"passed_time":0.2044774902,"remaining_time":1.513820747},
{"learn":[5.097271647],"iteration":119,"passed_time":0.2062312985,"remaining_time":1.512362856},
{"learn":[5.092186576],"iteration":120,"passed_time":0.2079214093,"remaining_time":1.510437345},
{"learn":[5.086788653],"iteration":121,"passed_time":0.2095643989,"remaining_time":1.508176576},
{"learn":[5.081820572],"iteration":122,"passed_time":0.2110078415,"remaining_time":1.504503065},
{"learn":[5.075684714],"iteration":123,"passed_time":0.2125026071,"remaining_time":1.501228096},
{"learn":[5.07057694],"iteration":124,"passed_time":0.2139219398,"remaining_time":1.497453578},
{"learn":[5.059957516],"iteration":125,"passed_time":0.2153933387,"remaining_time":1.494077603},
{"learn":[5.050764426],"iteration":126,"passed_time":0.2170097319,"remaining_time":1.491728315},
{"learn":[5.043171393],"iteration":127,"passed_time":0.2204749364,"remaining_time":1.501985504},
{"learn":[5.037264375],"iteration":128,"passed_time":0.2228280889,"remaining_time":1.504521437},
{"learn":[5.033686404],"iteration":129,"passed_time":0.2245380751,"remaining_time":1.502677887},
{"learn":[5.030654883],"iteration":130,"passed_time":0.2258911421,"remaining_time":1.498468721},
{"learn":[5.026164645],"iteration":131,"passed_time":0.227788385,"remaining_time":1.497881198},
{"learn":[5.020625375],"iteration":132,"passed_time":0.2294068596,"remaining_time":1.495456746},
{"learn":[5.015596553],"iteration":133,"passed_time":0.2307981291,"remaining_time":1.491575968},
{"learn":[5.009833745],"iteration":134,"passed_time":0.2322196285,"remaining_time":1.487925768},
{"learn":[5.00576763],"iteration":135,"passed_time":0.2350480896,"remaining_time":1.493246687},
{"learn":[5.002659849],"iteration":136,"passed_time":0.2365618936,"remaining_time":1.490167257},
{"learn":[4.998558855],"iteration":137,"passed_time":0.2380208491,"remaining_time":1.486767913},
{"learn":[4.994216136],"iteration":138,"passed_time":0.2394809951,"remaining_time":1.483403861},
{"learn":[4.988873446],"iteration":139,"passed_time":0.2410868756,"remaining_time":1.480962236},
{"learn":[4.98264557],"iteration":140,"passed_time":0.2425330934,"remaining_time":1.477559767},
{"learn":[4.976318318],"iteration":141,"passed_time":0.2440622227,"remaining_time":1.474685824},
{"learn":[4.970674184],"iteration":142,"passed_time":0.2455063052,"remaining_time":1.471321004},
{"learn":[4.964226284],"iteration":143,"passed_time":0.2469384318,"remaining_time":1.467911789},
{"learn":[4.960785624],"iteration":144,"passed_time":0.2497533482,"remaining_time":1.472683536},
{"learn":[4.959955949],"iteration":145,"passed_time":0.2508669468,"remaining_time":1.467399812},
{"learn":[4.956537156],"iteration":146,"passed_time":0.2522843827,"remaining_time":1.463935908},
{"learn":[4.953835323],"iteration":147,"passed_time":0.2537789519,"remaining_time":1.460943696},
{"learn":[4.950500911],"iteration":148,"passed_time":0.2553025498,"remaining_time":1.458137382},
{"learn":[4.943900021],"iteration":149,"passed_time":0.2568772112,"remaining_time":1.45563753},
{"learn":[4.940053398],"iteration":150,"passed_time":0.2584160806,"remaining_time":1.452948692},
{"learn":[4.936592963],"iteration":151,"passed_time":0.2598276542,"remaining_time":1.449564807},
{"learn":[4.932874605],"iteration":152,"passed_time":0.2613054079,"remaining_time":1.446573075},
{"learn":[4.927911115],"iteration":153,"passed_time":0.2630553244,"remaining_time":1.445096133},
{"learn":[4.924468172],"iteration":154,"passed_time":0.2655826423,"remaining_time":1.44785376},
{"learn":[4.917941092],"iteration":155,"passed_time":0.2671706801,"remaining_time":1.445461885},
{"learn":[4.913809206],"iteration":156,"passed_time":0.2685685236,"remaining_time":1.442059015},
{"learn":[4.907571176],"iteration":157,"passed_time":0.2702648977,"remaining_time":1.44027243},
{"learn":[4.902272713],"iteration":158,"passed_time":0.2717306202,"remaining_time":1.437266991},
{"learn":[4.895239901],"iteration":159,"passed_time":0.2731382914,"remaining_time":1.43397603},
{"learn":[4.892730062],"iteration":160,"passed_time":0.274504669,"remaining_time":1.430493275},
{"learn":[4.888383181],"iteration":161,"passed_time":0.275950189,"remaining_time":1.42744604},
{"learn":[4.883525706],"iteration":162,"passed_time":0.2773839915,"remaining_time":1.424358288},
{"learn":[4.877737475],"iteration":163,"passed_time":0.280299941,"remaining_time":1.428846041},
{"learn":[4.870725948],"iteration":164,"passed_time":0.2819532772,"remaining_time":1.426854463},
{"learn":[4.867654179],"iteration":165,"passed_time":0.2834724627,"remaining_time":1.424192975},
{"learn":[4.865022322],"iteration":166,"passed_time":0.2848845691,"remaining_time":1.421011054},
{"learn":[4.859958857],"iteration":167,"passed_time":0.2862674554,"remaining_time":1.417705494},
{"learn":[4.856573078],"iteration":168,"passed_time":0.2877326765,"remaining_time":1.414827539},
{"learn":[4.850945139],"iteration":169,"passed_time":0.2891315981,"remaining_time":1.411642508},
{"learn":[4.847706154],"iteration":170,"passed_time":0.2906148969,"remaining_time":1.408887424},
{"learn":[4.843568168],"iteration":171,"passed_time":0.2921283554,"remaining_time":1.406292316},
{"learn":[4.843312833],"iteration":172,"passed_time":0.2932538737,"remaining_time":1.401855223},
{"learn":[4.838654029],"iteration":173,"passed_time":0.2955876117,"remaining_time":1.403191766},
{"learn":[4.833881155],"iteration":174,"passed_time":0.2972161016,"remaining_time":1.401161622},
{"learn":[4.8297627],"iteration":175,"passed_time":0.2992263795,"remaining_time":1.400923504},
{"learn":[4.826153674],"iteration":176,"passed_time":0.3012880513,"remaining_time":1.400904329},
{"learn":[4.819255851],"iteration":177,"passed_time":0.3032588798,"remaining_time":1.400442692},
{"learn":[4.815221705],"iteration":178,"passed_time":0.3050753289,"remaining_time":1.399256117},
{"learn":[4.810586516],"iteration":179,"passed_time":0.3069693053,"remaining_time":1.398415724},
{"learn":[4.807242808],"iteration":180,"passed_time":0.3101456193,"remaining_time":1.403366089},
{"learn":[4.804768176],"iteration":181,"passed_time":0.3117132741,"remaining_time":1.400997023},
{"learn":[4.801420912],"iteration":182,"passed_time":0.3131514558,"remaining_time":1.398058685},
{"learn":[4.795717035],"iteration":183,"passed_time":0.3145589727,"remaining_time":1.395000662},
{"learn":[4.789928691],"iteration":184,"passed_time":0.3159598771,"remaining_time":1.39193135},
{"learn":[4.785082182],"iteration":185,"passed_time":0.3174151249,"remaining_time":1.389117805},
{"learn":[4.782246884],"iteration":186,"passed_time":0.3188438943,"remaining_time":1.386203669},
{"learn":[4.780434502],"iteration":187,"passed_time":0.3203376747,"remaining_time":1.383586127},
{"learn":[4.774332034],"iteration":188,"passed_time":0.3220005244,"remaining_time":1.381705954},
{"learn":[4.77022907],"iteration":189,"passed_time":0.3248497975,"remaining_time":1.384885979},
{"learn":[4.767335413],"iteration":190,"passed_time":0.3268421226,"remaining_time":1.384373179},
{"learn":[4.762757158],"iteration":191,"passed_time":0.3285220985,"remaining_time":1.382530498},
{"learn":[4.757436633],"iteration":192,"passed_time":0.3301255261,"remaining_time":1.380369428},
{"learn":[4.752428946],"iteration":193,"passed_time":0.3318174864,"remaining_time":1.378581928},
{"learn":[4.748706583],"iteration":194,"passed_time":0.3335371816,"remaining_time":1.376909904},
{"learn":[4.747731749],"iteration":195,"passed_time":0.3344635206,"remaining_time":1.371983013},
{"learn":[4.740564912],"iteration":196,"passed_time":0.3358577072,"remaining_time":1.369003751},
{"learn":[4.733930847],"iteration":197,"passed_time":0.3372984221,"remaining_time":1.366228962},
{"learn":[4.731157841],"iteration":198,"passed_time":0.3401876802,"remaining_time":1.36929815},
{"learn":[4.724740608],"iteration":199,"passed_time":0.3417425393,"remaining_time":1.366970157},
{"learn":[4.720662034],"iteration":200,"passed_time":0.343204526,"remaining_time":1.364280678},
{"learn":[4.715651385],"iteration":201,"passed_time":0.3446485857,"remaining_time":1.361532532},
{"learn":[4.710023093],"iteration":202,"passed_time":0.3462048425,"remaining_time":1.359237731},
{"learn":[4.708993332],"iteration":203,"passed_time":0.3476547487,"remaining_time":1.356535196},
{"learn":[4.705129668],"iteration":204,"passed_time":0.349084563,"remaining_time":1.353766964},
{"learn":[4.702672994],"iteration":205,"passed_time":0.3504850746,"remaining_time":1.350898783},
{"learn":[4.699022425],"iteration":206,"passed_time":0.3518900005,"remaining_time":1.348061693},
{"learn":[4.693223961],"iteration":207,"passed_time":0.3546511029,"remaining_time":1.350402276},
{"learn":[4.687096297],"iteration":208,"passed_time":0.3563407632,"remaining_time":1.348638965},
{"learn":[4.682625169],"iteration":209,"passed_time":0.3577800493,"remaining_time":1.345934471},
{"learn":[4.678017365],"iteration":210,"passed_time":0.3593304574,"remaining_time":1.343657492},
{"learn":[4.676785205],"iteration":211,"passed_time":0.3608844255,"remaining_time":1.341400601},
{"learn":[4.674005554],"iteration":212,"passed_time":0.3623422206,"remaining_time":1.338794965},
{"learn":[4.670349134],"iteration":213,"passed_time":0.3638050943,"remaining_time":1.336218711},
{"learn":[4.667924387],"iteration":214,"passed_time":0.3652157124,"remaining_time":1.33346202},
{"learn":[4.665169113],"iteration":215,"passed_time":0.3666301891,"remaining_time":1.330731797},
{"learn":[4.663233425],"iteration":216,"passed_time":0.3685398783,"remaining_time":1.329800575},
{"learn":[4.659409083],"iteration":217,"passed_time":0.3708549698,"remaining_time":1.330314616},
{"learn":[4.658945607],"iteration":218,"passed_time":0.3719257913,"remaining_time":1.326365493},
{"learn":[4.65346133],"iteration":219,"passed_time":0.3735389576,"remaining_time":1.324365395},
{"learn":[4.649566615],"iteration":220,"passed_time":0.3752464607,"remaining_time":1.322701325},
{"learn":[4.646512888],"iteration":221,"passed_time":0.3767253763,"remaining_time":1.320235778},
{"learn":[4.640337803],"iteration":222,"passed_time":0.378179688,"remaining_time":1.317693352},
{"learn":[4.635351786],"iteration":223,"passed_time":0.3796506504,"remaining_time":1.315218324},
{"learn":[4.630651806],"iteration":224,"passed_time":0.3813173805,"remaining_time":1.313426533},
{"learn":[4.623967985],"iteration":225,"passed_time":0.3832182373,"remaining_time":1.31243768},
{"learn":[4.620707251],"iteration":226,"passed_time":0.3855932874,"remaining_time":1.313055556},
{"learn":[4.619314009],"iteration":227,"passed_time":0.3870627859,"remaining_time":1.310581012},
{"learn":[4.615055791],"iteration":228,"passed_time":0.388652831,"remaining_time":1.308521103},
{"learn":[4.610351105],"iteration":229,"passed_time":0.3901296995,"remaining_time":1.306086385},
{"learn":[4.609119445],"iteration":230,"passed_time":0.3920738983,"remaining_time":1.305215705},
{"learn":[4.604574106],"iteration":231,"passed_time":0.3934941566,"remaining_time":1.302601346},
{"learn":[4.600879591],"iteration":232,"passed_time":0.3949666214,"remaining_time":1.300169093},
{"learn":[4.598747616],"iteration":233,"passed_time":0.3965368935,"remaining_time":1.298065216},
{"learn":[4.593116669],"iteration":234,"passed_time":0.3995532296,"remaining_time":1.300673279},
{"learn":[4.589436328],"iteration":235,"passed_time":0.4012474847,"remaining_time":1.298953722},
{"learn":[4.585322861],"iteration":236,"passed_time":0.4031121169,"remaining_time":1.297782891},
{"learn":[4.583562195],"iteration":237,"passed_time":0.4045322384,"remaining_time":1.295183049},
{"learn":[4.580352406],"iteration":238,"passed_time":0.4059846393,"remaining_time":1.29269586},
{"learn":[4.578244708],"iteration":239,"passed_time":0.4073961427,"remaining_time":1.290087785},
{"learn":[4.574445652],"iteration":240,"passed_time":0.4088649243,"remaining_time":1.287670031},
{"learn":[4.572616329],"iteration":241,"passed_time":0.4102592686,"remaining_time":1.285026965},
{"learn":[4.568569882],"iteration":242,"passed_time":0.4120636421,"remaining_time":1.28367151},
{"learn":[4.565451196],"iteration":243,"passed_time":0.4159375994,"remaining_time":1.288724693},
{"learn":[4.564897004],"iteration":244,"passed_time":0.4176682587,"remaining_time":1.287100144},
{"learn":[4.560493036],"iteration":245,"passed_time":0.4192661238,"remaining_time":1.285067713},
{"learn":[4.555997674],"iteration":246,"passed_time":0.4208793515,"remaining_time":1.283085634},
{"learn":[4.555475669],"iteration":247,"passed_time":0.4226205701,"remaining_time":1.281494632},
{"learn":[4.55343604],"iteration":248,"passed_time":0.4246297466,"remaining_time":1.280710601},
{"learn":[4.551038265],"iteration":249,"passed_time":0.4260750036,"remaining_time":1.278225011},
{"learn":[4.547724663],"iteration":250,"passed_time":0.4275165004,"remaining_time":1.275736489},
{"learn":[4.544745865],"iteration":251,"passed_time":0.4304188758,"remaining_time":1.277592536},
{"learn":[4.544025113],"iteration":252,"passed_time":0.4319203259,"remaining_time":1.275274638},
{"learn":[4.538907613],"iteration":253,"passed_time":0.4334011966,"remaining_time":1.272902727},
{"learn":[4.533521064],"iteration":254,"passed_time":0.4351945401,"remaining_time":1.271450715},
{"learn":[4.533325069],"iteration":255,"passed_time":0.4365326666,"remaining_time":1.268673062},
{"learn":[4.527570301],"iteration":256,"passed_time":0.4382838737,"remaining_time":1.267100849},
{"learn":[4.523634362],"iteration":257,"passed_time":0.4399438838,"remaining_time":1.265264968},
{"learn":[4.521070074],"iteration":258,"passed_time":0.4415859246,"remaining_time":1.263379035},
{"learn":[4.518969023],"iteration":259,"passed_time":0.4454969742,"remaining_time":1.267952927},
{"learn":[4.518666992],"iteration":260,"passed_time":0.4471693238,"remaining_time":1.266123105},
{"learn":[4.51737024],"iteration":261,"passed_time":0.4486546088,"remaining_time":1.263767562},
{"learn":[4.510577735],"iteration":262,"passed_time":0.4502196585,"remaining_time":1.261642161},
{"learn":[4.507078825],"iteration":263,"passed_time":0.4516813524,"remaining_time":1.259232861},
{"learn":[4.503501645],"iteration":264,"passed_time":0.4530949438,"remaining_time":1.256697297},
{"learn":[4.502853121],"iteration":265,"passed_time":0.4544712332,"remaining_time":1.254067238},
{"learn":[4.497212533],"iteration":266,"passed_time":0.455916897,"remaining_time":1.251637024},
{"learn":[4.493816837],"iteration":267,"passed_time":0.4583349745,"remaining_time":1.251870154},
{"learn":[4.49083451],"iteration":268,"passed_time":0.46067359,"remaining_time":1.251867637},
{"learn":[4.486445272],"iteration":269,"passed_time":0.4621482146,"remaining_time":1.249511839},
{"learn":[4.484250647],"iteration":270,"passed_time":0.463564106,"remaining_time":1.247004551},
{"learn":[4.481076671],"iteration":271,"passed_time":0.4651920226,"remaining_time":1.245072766},
{"learn":[4.475884433],"iteration":272,"passed_time":0.466713668,"remaining_time":1.242860208},
{"learn":[4.473335782],"iteration":273,"passed_time":0.4684207193,"remaining_time":1.24114395},
{"learn":[4.472113702],"iteration":274,"passed_time":0.4698538363,"remaining_time":1.238705568},
{"learn":[4.467740263],"iteration":275,"passed_time":0.4712956416,"remaining_time":1.236297263},
{"learn":[4.46681499],"iteration":276,"passed_time":0.4728364726,"remaining_time":1.234154403},
{"learn":[4.466586071],"iteration":277,"passed_time":0.475450377,"remaining_time":1.234802778},
{"learn":[4.463346793],"iteration":278,"passed_time":0.4769287654,"remaining_time":1.232493333},
{"learn":[4.45867567],"iteration":279,"passed_time":0.4785860359,"remaining_time":1.230649807},
{"learn":[4.457082557],"iteration":280,"passed_time":0.4801560153,"remaining_time":1.228584253},
{"learn":[4.454067031],"iteration":281,"passed_time":0.4815414734,"remaining_time":1.226052404},
{"learn":[4.453731236],"iteration":282,"passed_time":0.4828674321,"remaining_time":1.223377911},
{"learn":[4.450692799],"iteration":283,"passed_time":0.4842779293,"remaining_time":1.220926047},
{"learn":[4.446940512],"iteration":284,"passed_time":0.4857271606,"remaining_time":1.218578666},
{"learn":[4.445881219],"iteration":285,"passed_time":0.4872752494,"remaining_time":1.216484364},
{"learn":[4.443308309],"iteration":286,"passed_time":0.4906460049,"remaining_time":1.218921956},
{"learn":[4.439251054],"iteration":287,"passed_time":0.4921345576,"remaining_time":1.21666599},
{"learn":[4.43379503],"iteration":288,"passed_time":0.4935923912,"remaining_time":1.214339758},
{"learn":[4.430597232],"iteration":289,"passed_time":0.4949587092,"remaining_time":1.21179546},
{"learn":[4.42696425],"iteration":290,"passed_time":0.4964017749,"remaining_time":1.209446249},
{"learn":[4.424827832],"iteration":291,"passed_time":0.4978300851,"remaining_time":1.207067467},
{"learn":[4.423090404],"iteration":292,"passed_time":0.4992654689,"remaining_time":1.204712241},
{"learn":[4.416467285],"iteration":293,"passed_time":0.5013100947,"remaining_time":1.203826282},
{"learn":[4.413728271],"iteration":294,"passed_time":0.5055467161,"remaining_time":1.208170966},
{"learn":[4.413498144],"iteration":295,"passed_time":0.5073842506,"remaining_time":1.206751731},
{"learn":[4.410329979],"iteration":296,"passed_time":0.5091561787,"remaining_time":1.205174389},
{"learn":[4.407110924],"iteration":297,"passed_time":0.510757265,"remaining_time":1.203193289},
{"learn":[4.404917361],"iteration":298,"passed_time":0.5131572503,"remaining_time":1.203087734},
{"learn":[4.401028912],"iteration":299,"passed_time":0.5148309463,"remaining_time":1.201272208},
{"learn":[4.394665046],"iteration":300,"passed_time":0.5164846611,"remaining_time":1.199411223},
{"learn":[4.394483882],"iteration":301,"passed_time":0.5187893381,"remaining_time":1.199056152},
{"learn":[4.389618438],"iteration":302,"passed_time":0.5216296749,"remaining_time":1.199920407},
{"learn":[4.384869123],"iteration":303,"passed_time":0.5238715906,"remaining_time":1.199390221},
{"learn":[4.382466908],"iteration":304,"passed_time":0.5264602626,"remaining_time":1.199638959},
{"learn":[4.380932647],"iteration":305,"passed_time":0.5305225362,"remaining_time":1.203211242},
{"learn":[4.374248057],"iteration":306,"passed_time":0.5322443105,"remaining_time":1.201450512},
{"learn":[4.371096405],"iteration":307,"passed_time":0.5382325533,"remaining_time":1.209275737},
{"learn":[4.368374177],"iteration":308,"passed_time":0.5407735851,"remaining_time":1.209302742},
{"learn":[4.365950023],"iteration":309,"passed_time":0.5432130768,"remaining_time":1.209087171},
{"learn":[4.362319533],"iteration":310,"passed_time":0.5547522957,"remaining_time":1.229017144},
{"learn":[4.358766357],"iteration":311,"passed_time":0.5599268382,"remaining_time":1.234710464},
{"learn":[4.355339363],"iteration":312,"passed_time":0.5616971666,"remaining_time":1.232862471},
{"learn":[4.351722143],"iteration":313,"passed_time":0.5634684959,"remaining_time":1.23101716},
{"learn":[4.350800369],"iteration":314,"passed_time":0.5726997838,"remaining_time":1.245394768},
{"learn":[4.344857226],"iteration":315,"passed_time":0.5744733513,"remaining_time":1.243480292},
{"learn":[4.340492216],"iteration":316,"passed_time":0.5762182505,"remaining_time":1.241504937},
{"learn":[4.33797595],"iteration":317,"passed_time":0.5779328859,"remaining_time":1.239466126},
{"learn":[4.336158783],"iteration":318,"passed_time":0.5825818934,"remaining_time":1.243693635},
{"learn":[4.330012488],"iteration":319,"passed_time":0.5850332311,"remaining_time":1.243195616},
{"learn":[4.329810893],"iteration":320,"passed_time":0.5867768294,"remaining_time":1.241188371},
{"learn":[4.329637208],"iteration":321,"passed_time":0.5884441118,"remaining_time":1.239022074},
{"learn":[4.326178808],"iteration":322,"passed_time":0.5919636926,"remaining_time":1.240741238},
{"learn":[4.321633721],"iteration":323,"passed_time":0.5936327977,"remaining_time":1.238567195},
{"learn":[4.320821061],"iteration":324,"passed_time":0.5963190912,"remaining_time":1.238508882},
{"learn":[4.316740072],"iteration":325,"passed_time":0.599840195,"remaining_time":1.240160403},
{"learn":[4.316581002],"iteration":326,"passed_time":0.6079152661,"remaining_time":1.251152826},
{"learn":[4.31233317],"iteration":327,"passed_time":0.6100170311,"remaining_time":1.249790991},
{"learn":[4.310003927],"iteration":328,"passed_time":0.6193392999,"remaining_time":1.263150973},
{"learn":[4.305083371],"iteration":329,"passed_time":0.6213193473,"remaining_time":1.261466554},
{"learn":[4.301759597],"iteration":330,"passed_time":0.6231964386,"remaining_time":1.259572258},
{"learn":[4.299526989],"iteration":331,"passed_time":0.6261562026,"remaining_time":1.259856456},
{"learn":[4.29909731],"iteration":332,"passed_time":0.6346796132,"remaining_time":1.271265171},
{"learn":[4.298634573],"iteration":333,"passed_time":0.6382586744,"remaining_time":1.272695441},
{"learn":[4.291873649],"iteration":334,"passed_time":0.6400975807,"remaining_time":1.270641466},
{"learn":[4.289205683],"iteration":335,"passed_time":0.6431886827,"remaining_time":1.271063349},
{"learn":[4.286424349],"iteration":336,"passed_time":0.6509018448,"remaining_time":1.280557635},
{"learn":[4.282626354],"iteration":337,"passed_time":0.6526515601,"remaining_time":1.278270215},
{"learn":[4.281229695],"iteration":338,"passed_time":0.6543333798,"remaining_time":1.275853581},
{"learn":[4.274032826],"iteration":339,"passed_time":0.6559205427,"remaining_time":1.273257524},
{"learn":[4.270239889],"iteration":340,"passed_time":0.6651750329,"remaining_time":1.285484888},
{"learn":[4.26341248],"iteration":341,"passed_time":0.6707173573,"remaining_time":1.290444506},
{"learn":[4.258148328],"iteration":342,"passed_time":0.6726688822,"remaining_time":1.288464885},
{"learn":[4.254539379],"iteration":343,"passed_time":0.6809031064,"remaining_time":1.298466389},
{"learn":[4.250218586],"iteration":344,"passed_time":0.6828683979,"remaining_time":1.296460292},
{"learn":[4.249971191],"iteration":345,"passed_time":0.6843930656,"remaining_time":1.293621575},
{"learn":[4.246038989],"iteration":346,"passed_time":0.6859860817,"remaining_time":1.290919053},
{"learn":[4.243306971],"iteration":347,"passed_time":0.6966043176,"remaining_time":1.305132227},
{"learn":[4.240635921],"iteration":348,"passed_time":0.6996936196,"remaining_time":1.305159159},
{"learn":[4.237304693],"iteration":349,"passed_time":0.7026666307,"remaining_time":1.304952314},
{"learn":[4.231139968],"iteration":350,"passed_time":0.7055759738,"remaining_time":1.304611986},
{"learn":[4.229131441],"iteration":351,"passed_time":0.7092244908,"remaining_time":1.305617813},
{"learn":[4.224376835],"iteration":352,"passed_time":0.7164138684,"remaining_time":1.313087175},
{"learn":[4.219225034],"iteration":353,"passed_time":0.7181539045,"remaining_time":1.310529442},
{"learn":[4.216749851],"iteration":354,"passed_time":0.7198862398,"remaining_time":1.307962323},
{"learn":[4.213618749],"iteration":355,"passed_time":0.7279531223,"remaining_time":1.316859019},
{"learn":[4.21196936],"iteration":356,"passed_time":0.730856966,"remaining_time":1.316361426},
{"learn":[4.206405341],"iteration":357,"passed_time":0.7326284066,"remaining_time":1.313819657},
{"learn":[4.2006312],"iteration":358,"passed_time":0.7365130529,"remaining_time":1.315055339},
{"learn":[4.198065921],"iteration":359,"passed_time":0.7433237769,"remaining_time":1.321464492},
{"learn":[4.191388233],"iteration":360,"passed_time":0.7487858728,"remaining_time":1.325413221},
{"learn":[4.187783537],"iteration":361,"passed_time":0.7533707691,"remaining_time":1.327763952},
{"learn":[4.181147054],"iteration":362,"passed_time":0.7573538736,"remaining_time":1.329020434},
{"learn":[4.176263823],"iteration":363,"passed_time":0.7598911271,"remaining_time":1.327721859},
{"learn":[4.171755481],"iteration":364,"passed_time":0.764032469,"remaining_time":1.329207172},
{"learn":[4.168357465],"iteration":365,"passed_time":0.7727798652,"remaining_time":1.338640531},
{"learn":[4.162705645],"iteration":366,"passed_time":0.7746906347,"remaining_time":1.336183029},
{"learn":[4.161320939],"iteration":367,"passed_time":0.776464421,"remaining_time":1.333493245},
{"learn":[4.157684744],"iteration":368,"passed_time":0.7843738566,"remaining_time":1.341300552},
{"learn":[4.152874642],"iteration":369,"passed_time":0.7881847415,"remaining_time":1.34204429},
{"learn":[4.15211191],"iteration":370,"passed_time":0.7911946503,"remaining_time":1.341405485},
{"learn":[4.148989309],"iteration":371,"passed_time":0.7930112536,"remaining_time":1.338739428},
{"learn":[4.14455489],"iteration":372,"passed_time":0.7947491966,"remaining_time":1.3359457},
{"learn":[4.140348217],"iteration":373,"passed_time":0.805654297,"remaining_time":1.348501577},
{"learn":[4.136399553],"iteration":374,"passed_time":0.8088661312,"remaining_time":1.348110219},
{"learn":[4.134762348],"iteration":375,"passed_time":0.8112466925,"remaining_time":1.346324298},
{"learn":[4.131267949],"iteration":376,"passed_time":0.8132369324,"remaining_time":1.343890209},
{"learn":[4.127762691],"iteration":377,"passed_time":0.8164101035,"remaining_time":1.343404985},
{"learn":[4.12459648],"iteration":378,"passed_time":0.8185372933,"remaining_time":1.341191713},
{"learn":[4.117807469],"iteration":379,"passed_time":0.8222615343,"remaining_time":1.341584609},
{"learn":[4.114466884],"iteration":380,"passed_time":0.8248712625,"remaining_time":1.340145174},
{"learn":[4.1122779],"iteration":381,"passed_time":0.8281124081,"remaining_time":1.339721121},
{"learn":[4.109742839],"iteration":382,"passed_time":0.8304882151,"remaining_time":1.337888326},
{"learn":[4.107836197],"iteration":383,"passed_time":0.8339466373,"remaining_time":1.337789397},
{"learn":[4.106976181],"iteration":384,"passed_time":0.8438139537,"remaining_time":1.347910601},
{"learn":[4.10267537],"iteration":385,"passed_time":0.8458366319,"remaining_time":1.345449979},
{"learn":[4.100770102],"iteration":386,"passed_time":0.8476723858,"remaining_time":1.342695536},
{"learn":[4.100145082],"iteration":387,"passed_time":0.8567631329,"remaining_time":1.351389271},
{"learn":[4.09725971],"iteration":388,"passed_time":0.8619077812,"remaining_time":1.353793456},
{"learn":[4.092853304],"iteration":389,"passed_time":0.86382638,"remaining_time":1.351113056},
{"learn":[4.091136542],"iteration":390,"passed_time":0.865596739,"remaining_time":1.348205663},
{"learn":[4.088490766],"iteration":391,"passed_time":0.8740607125,"remaining_time":1.355686003},
{"learn":[4.084062936],"iteration":392,"passed_time":0.8778329206,"remaining_time":1.355838633},
{"learn":[4.079058405],"iteration":393,"passed_time":0.8802888149,"remaining_time":1.353946756},
{"learn":[4.078871947],"iteration":394,"passed_time":0.8867832651,"remaining_time":1.358237659},
{"learn":[4.074624708],"iteration":395,"passed_time":0.889165043,"remaining_time":1.356201227},
{"learn":[4.072593097],"iteration":396,"passed_time":0.8920054311,"remaining_time":1.354859635},
{"learn":[4.071250214],"iteration":397,"passed_time":0.8941661226,"remaining_time":1.352482427},
{"learn":[4.069476207],"iteration":398,"passed_time":0.8964779047,"remaining_time":1.350333887},
{"learn":[4.067015741],"iteration":399,"passed_time":0.9055253711,"remaining_time":1.358288057},
{"learn":[4.063906833],"iteration":400,"passed_time":0.9093688026,"remaining_time":1.358383822},
{"learn":[4.059024276],"iteration":401,"passed_time":0.9174499227,"remaining_time":1.364763815},
{"learn":[4.055262463],"iteration":402,"passed_time":0.9194447977,"remaining_time":1.362055941},
{"learn":[4.049931988],"iteration":403,"passed_time":0.923169885,"remaining_time":1.361904088},
{"learn":[4.045893313],"iteration":404,"passed_time":0.9251740455,"remaining_time":1.359206314},
{"learn":[4.044414933],"iteration":405,"passed_time":0.9269060718,"remaining_time":1.35611381},
{"learn":[4.040552139],"iteration":406,"passed_time":0.9291742511,"remaining_time":1.353809167},
{"learn":[4.03647419],"iteration":407,"passed_time":0.9362798761,"remaining_time":1.358523742},
{"learn":[4.03297515],"iteration":408,"passed_time":0.9382100934,"remaining_time":1.355702115},
{"learn":[4.028628465],"iteration":409,"passed_time":0.9401931579,"remaining_time":1.352960886},
{"learn":[4.027732183],"iteration":410,"passed_time":0.9422593688,"remaining_time":1.350342502},
{"learn":[4.023542478],"iteration":411,"passed_time":0.949553254,"remaining_time":1.355187654},
{"learn":[4.019366171],"iteration":412,"passed_time":0.9516921284,"remaining_time":1.352647166},
{"learn":[4.01548812],"iteration":413,"passed_time":0.953597481,"remaining_time":1.349778077},
{"learn":[4.012777105],"iteration":414,"passed_time":0.9552388341,"remaining_time":1.346541489},
{"learn":[4.009857772],"iteration":415,"passed_time":0.9568943879,"remaining_time":1.343332506},
{"learn":[4.007161013],"iteration":416,"passed_time":0.9586034893,"remaining_time":1.340205838},
{"learn":[4.004553966],"iteration":417,"passed_time":0.9613353264,"remaining_time":1.338509952},
{"learn":[4.000859867],"iteration":418,"passed_time":0.9642832931,"remaining_time":1.337108815},
{"learn":[4.000439959],"iteration":419,"passed_time":0.9663102247,"remaining_time":1.334428406},
{"learn":[3.9948522],"iteration":420,"passed_time":0.9681207466,"remaining_time":1.331453473},
{"learn":[3.993556923],"iteration":421,"passed_time":0.969846355,"remaining_time":1.328367756},
{"learn":[3.991337292],"iteration":422,"passed_time":0.9716855834,"remaining_time":1.325443455},
{"learn":[3.987292366],"iteration":423,"passed_time":0.973882442,"remaining_time":1.32301011},
{"learn":[3.984475652],"iteration":424,"passed_time":0.9777213787,"remaining_time":1.322799512},
{"learn":[3.982118789],"iteration":425,"passed_time":0.9792208512,"remaining_time":1.319419645},
{"learn":[3.979451774],"iteration":426,"passed_time":0.9806914122,"remaining_time":1.316009787},
{"learn":[3.976705165],"iteration":427,"passed_time":0.9824914827,"remaining_time":1.313049365},
{"learn":[3.975682594],"iteration":428,"passed_time":0.9841040753,"remaining_time":1.309844818},
{"learn":[3.97350583],"iteration":429,"passed_time":0.985643446,"remaining_time":1.306550615},
{"learn":[3.972732269],"iteration":430,"passed_time":0.9870893114,"remaining_time":1.30314111},
{"learn":[3.969151867],"iteration":431,"passed_time":0.9893199978,"remaining_time":1.30077259},
{"learn":[3.96756418],"iteration":432,"passed_time":0.9922287982,"remaining_time":1.299292676},
{"learn":[3.963960966],"iteration":433,"passed_time":0.9936710541,"remaining_time":1.295893587},
{"learn":[3.960229281],"iteration":434,"passed_time":0.9951403177,"remaining_time":1.292538574},
{"learn":[3.958407547],"iteration":435,"passed_time":0.9966599454,"remaining_time":1.289257361},
{"learn":[3.95735904],"iteration":436,"passed_time":0.9984692589,"remaining_time":1.286357421},
{"learn":[3.956969292],"iteration":437,"passed_time":0.9999588793,"remaining_time":1.283052261},
{"learn":[3.952722281],"iteration":438,"passed_time":1.001476068,"remaining_time":1.279790602},
{"learn":[3.952251354],"iteration":439,"passed_time":1.00352044,"remaining_time":1.277207833},
{"learn":[3.949940175],"iteration":440,"passed_time":1.006520226,"remaining_time":1.275838563},
{"learn":[3.945738433],"iteration":441,"passed_time":1.008010483,"remaining_time":1.27255622},
{"learn":[3.943666906],"iteration":442,"passed_time":1.009474927,"remaining_time":1.269249514},
{"learn":[3.940810005],"iteration":443,"passed_time":1.011156453,"remaining_time":1.266222945},
{"learn":[3.938410483],"iteration":444,"passed_time":1.012615017,"remaining_time":1.262924347},
{"learn":[3.936793216],"iteration":445,"passed_time":1.014130702,"remaining_time":1.259704953},
{"learn":[3.934528189],"iteration":446,"passed_time":1.015640327,"remaining_time":1.256485684},
{"learn":[3.932451252],"iteration":447,"passed_time":1.01707211,"remaining_time":1.253178135},
{"learn":[3.930087721],"iteration":448,"passed_time":1.021293827,"remaining_time":1.253302669},
{"learn":[3.929082991],"iteration":449,"passed_time":1.022743186,"remaining_time":1.250019449},
{"learn":[3.927413667],"iteration":450,"passed_time":1.024199184,"remaining_time":1.246752443},
{"learn":[3.925438611],"iteration":451,"passed_time":1.025947428,"remaining_time":1.243847767},
{"learn":[3.922985612],"iteration":452,"passed_time":1.027390141,"remaining_time":1.240579266},
{"learn":[3.921984031],"iteration":453,"passed_time":1.028815096,"remaining_time":1.23729745},
{"learn":[3.921193862],"iteration":454,"passed_time":1.030291851,"remaining_time":1.234085843},
{"learn":[3.920374594],"iteration":455,"passed_time":1.031691433,"remaining_time":1.23078978},
{"learn":[3.915768353],"iteration":456,"passed_time":1.035373774,"remaining_time":1.230214352},
{"learn":[3.915235953],"iteration":457,"passed_time":1.037646237,"remaining_time":1.2279569},
{"learn":[3.910713373],"iteration":458,"passed_time":1.039283451,"remaining_time":1.224950648},
{"learn":[3.908755689],"iteration":459,"passed_time":1.0409106,"remaining_time":1.221938531},
{"learn":[3.907824914],"iteration":460,"passed_time":1.042336297,"remaining_time":1.218696885},
{"learn":[3.906210524],"iteration":461,"passed_time":1.043751487,"remaining_time":1.215450865},
{"learn":[3.90520368],"iteration":462,"passed_time":1.045149458,"remaining_time":1.212192784},
{"learn":[3.903381259],"iteration":463,"passed_time":1.04656647,"remaining_time":1.208964715},
{"learn":[3.900774775],"iteration":464,"passed_time":1.048674765,"remaining_time":1.206539784},
{"learn":[3.896833077],"iteration":465,"passed_time":1.052237624,"remaining_time":1.205783029},
{"learn":[3.894446184],"iteration":466,"passed_time":1.054029169,"remaining_time":1.202992606},
{"learn":[3.893319574],"iteration":467,"passed_time":1.055686225,"remaining_time":1.200053572},
{"learn":[3.890740927],"iteration":468,"passed_time":1.057303017,"remaining_time":1.197074418},
{"learn":[3.888249807],"iteration":469,"passed_time":1.058921227,"remaining_time":1.19410266},
{"learn":[3.884193647],"iteration":470,"passed_time":1.060760832,"remaining_time":1.191385308},
{"learn":[3.882234757],"iteration":471,"passed_time":1.0622923,"remaining_time":1.18832698},
{"learn":[3.882069851],"iteration":472,"passed_time":1.066829626,"remaining_time":1.188624129},
{"learn":[3.880747043],"iteration":473,"passed_time":1.068948917,"remaining_time":1.186217574},
{"learn":[3.878295276],"iteration":474,"passed_time":1.070674055,"remaining_time":1.183376587},
{"learn":[3.876372175],"iteration":475,"passed_time":1.072495325,"remaining_time":1.180646114},
{"learn":[3.871359121],"iteration":476,"passed_time":1.073970625,"remaining_time":1.177540119},
{"learn":[3.869201202],"iteration":477,"passed_time":1.075459594,"remaining_time":1.174455875},
{"learn":[3.866815923],"iteration":478,"passed_time":1.076950761,"remaining_time":1.171380682},
{"learn":[3.865083309],"iteration":479,"passed_time":1.079466382,"remaining_time":1.169421914},
{"learn":[3.864499485],"iteration":480,"passed_time":1.083079343,"remaining_time":1.168644863},
{"learn":[3.862143282],"iteration":481,"passed_time":1.084879394,"remaining_time":1.165907731},
{"learn":[3.861395265],"iteration":482,"passed_time":1.086567884,"remaining_time":1.163055064},
{"learn":[3.860825849],"iteration":483,"passed_time":1.087966802,"remaining_time":1.159898492},
{"learn":[3.859269866],"iteration":484,"passed_time":1.089370021,"remaining_time":1.156753733},
{"learn":[3.85579738],"iteration":485,"passed_time":1.090843101,"remaining_time":1.153690028},
{"learn":[3.852276252],"iteration":486,"passed_time":1.095961774,"remaining_time":1.15447308},
{"learn":[3.848503219],"iteration":487,"passed_time":1.098125059,"remaining_time":1.15213121},
{"learn":[3.844789524],"iteration":488,"passed_time":1.099798488,"remaining_time":1.149278174},
{"learn":[3.844246604],"iteration":489,"passed_time":1.101686401,"remaining_time":1.146653192},
{"learn":[3.841774962],"iteration":490,"passed_time":1.103360277,"remaining_time":1.14380933},
{"learn":[3.839934619],"iteration":491,"passed_time":1.104750711,"remaining_time":1.140677563},
{"learn":[3.836798054],"iteration":492,"passed_time":1.106220925,"remaining_time":1.137634906},
{"learn":[3.833444652],"iteration":493,"passed_time":1.112268174,"remaining_time":1.139286834},
{"learn":[3.833312062],"iteration":494,"passed_time":1.114572132,"remaining_time":1.13708874},
{"learn":[3.829886165],"iteration":495,"passed_time":1.117073896,"remaining_time":1.135091217},
{"learn":[3.826298396],"iteration":496,"passed_time":1.12062706,"remaining_time":1.134155756},
{"learn":[3.823681139],"iteration":497,"passed_time":1.122174403,"remaining_time":1.131187852},
{"learn":[3.821113215],"iteration":498,"passed_time":1.126966938,"remaining_time":1.13148384},
{"learn":[3.819448565],"iteration":499,"passed_time":1.128834158,"remaining_time":1.128834158},
{"learn":[3.817970106],"iteration":500,"passed_time":1.130753163,"remaining_time":1.126239178},
{"learn":[3.812234755],"iteration":501,"passed_time":1.132538595,"remaining_time":1.123514383},
{"learn":[3.809496282],"iteration":502,"passed_time":1.134038384,"remaining_time":1.120511088},
{"learn":[3.806858046],"iteration":503,"passed_time":1.135551031,"remaining_time":1.117526412},
{"learn":[3.803818],"iteration":504,"passed_time":1.1372331,"remaining_time":1.114713633},
{"learn":[3.802578822],"iteration":505,"passed_time":1.141521352,"remaining_time":1.114449699},
{"learn":[3.799966446],"iteration":506,"passed_time":1.143852862,"remaining_time":1.112267182},
{"learn":[3.795617609],"iteration":507,"passed_time":1.145703254,"remaining_time":1.109618112},
{"learn":[3.794503483],"iteration":508,"passed_time":1.147391929,"remaining_time":1.106816183},
{"learn":[3.793830343],"iteration":509,"passed_time":1.149187541,"remaining_time":1.104121363},
{"learn":[3.792498287],"iteration":510,"passed_time":1.15070739,"remaining_time":1.101166171},
{"learn":[3.790800236],"iteration":511,"passed_time":1.153603149,"remaining_time":1.099528002},
{"learn":[3.788339165],"iteration":512,"passed_time":1.156204415,"remaining_time":1.09760536},
{"learn":[3.784614191],"iteration":513,"passed_time":1.157791334,"remaining_time":1.094720989},
{"learn":[3.781209212],"iteration":514,"passed_time":1.159241827,"remaining_time":1.091713177},
{"learn":[3.776575958],"iteration":515,"passed_time":1.160692109,"remaining_time":1.088711203},
{"learn":[3.773090452],"iteration":516,"passed_time":1.162705411,"remaining_time":1.086241225},
{"learn":[3.770642268],"iteration":517,"passed_time":1.164114837,"remaining_time":1.083211103},
{"learn":[3.767709131],"iteration":518,"passed_time":1.165549851,"remaining_time":1.08021094},
{"learn":[3.764907999],"iteration":519,"passed_time":1.167694827,"remaining_time":1.077872148},
{"learn":[3.763232259],"iteration":520,"passed_time":1.170905487,"remaining_time":1.076513874},
{"learn":[3.759267507],"iteration":521,"passed_time":1.172797564,"remaining_time":1.073941065},
{"learn":[3.759225174],"iteration":522,"passed_time":1.173568334,"remaining_time":1.070348174},
{"learn":[3.757425654],"iteration":523,"passed_time":1.174984797,"remaining_time":1.067352602},
{"learn":[3.753460575],"iteration":524,"passed_time":1.176625251,"remaining_time":1.064565704},
{"learn":[3.748860666],"iteration":525,"passed_time":1.178134741,"remaining_time":1.061665147},
{"learn":[3.746486573],"iteration":526,"passed_time":1.179553769,"remaining_time":1.058688677},
{"learn":[3.746105708],"iteration":527,"passed_time":1.180970496,"remaining_time":1.05571605},
{"learn":[3.744676112],"iteration":528,"passed_time":1.185546973,"remaining_time":1.055562617},
{"learn":[3.7434364],"iteration":529,"passed_time":1.186978088,"remaining_time":1.05260321},
{"learn":[3.741455563],"iteration":530,"passed_time":1.188411682,"remaining_time":1.049651749},
{"learn":[3.739916854],"iteration":531,"passed_time":1.189890204,"remaining_time":1.046745517},
{"learn":[3.738438464],"iteration":532,"passed_time":1.191390207,"remaining_time":1.043863465},
{"learn":[3.7368485],"iteration":533,"passed_time":1.192822402,"remaining_time":1.040927415},
{"learn":[3.735330424],"iteration":534,"passed_time":1.194374868,"remaining_time":1.038101521},
{"learn":[3.734491746],"iteration":535,"passed_time":1.196105087,"remaining_time":1.035434255},
{"learn":[3.732394239],"iteration":536,"passed_time":1.203314601,"remaining_time":1.037494712},
{"learn":[3.730279033],"iteration":537,"passed_time":1.205177911,"remaining_time":1.034929731},
{"learn":[3.726986091],"iteration":538,"passed_time":1.2070632,"remaining_time":1.03238615},
{"learn":[3.72397932],"iteration":539,"passed_time":1.208546211,"remaining_time":1.029502328},
{"learn":[3.723899055],"iteration":540,"passed_time":1.209910932,"remaining_time":1.026523323},
{"learn":[3.722417888],"iteration":541,"passed_time":1.211309976,"remaining_time":1.023579279},
{"learn":[3.720792402],"iteration":542,"passed_time":1.214289127,"remaining_time":1.021970775},
{"learn":[3.718413168],"iteration":543,"passed_time":1.217766854,"remaining_time":1.020775157},
{"learn":[3.716094786],"iteration":544,"passed_time":1.219490954,"remaining_time":1.018107127},
{"learn":[3.714149944],"iteration":545,"passed_time":1.221163189,"remaining_time":1.015399428},
{"learn":[3.712426033],"iteration":546,"passed_time":1.222709791,"remaining_time":1.012591472},
{"learn":[3.709643176],"iteration":547,"passed_time":1.224288469,"remaining_time":1.009814577},
{"learn":[3.705053476],"iteration":548,"passed_time":1.228548874,"remaining_time":1.009245068},
{"learn":[3.701953828],"iteration":549,"passed_time":1.232897553,"remaining_time":1.008734362},
{"learn":[3.700990918],"iteration":550,"passed_time":1.234729875,"remaining_time":1.00615919},
{"learn":[3.697587046],"iteration":551,"passed_time":1.236303839,"remaining_time":1.003377029},
{"learn":[3.696797268],"iteration":552,"passed_time":1.239769243,"remaining_time":1.002128122},
{"learn":[3.694513645],"iteration":553,"passed_time":1.241402994,"remaining_time":0.9993966343},
{"learn":[3.69305155],"iteration":554,"passed_time":1.24797574,"remaining_time":1.000629197},
{"learn":[3.692232976],"iteration":555,"passed_time":1.251764662,"remaining_time":0.9996106293},
{"learn":[3.689439731],"iteration":556,"passed_time":1.253486445,"remaining_time":0.996938052},
{"learn":[3.687179131],"iteration":557,"passed_time":1.255039244,"remaining_time":0.9941350286},
{"learn":[3.684167617],"iteration":558,"passed_time":1.25664328,"remaining_time":0.991376899},
{"learn":[3.682884681],"iteration":559,"passed_time":1.268009431,"remaining_time":0.996293124},
{"learn":[3.681865771],"iteration":560,"passed_time":1.269607966,"remaining_time":0.9935078377},
{"learn":[3.680192961],"iteration":561,"passed_time":1.271678076,"remaining_time":0.9910943009},
{"learn":[3.676271057],"iteration":562,"passed_time":1.280858,"remaining_time":0.9942006147},
{"learn":[3.673365593],"iteration":563,"passed_time":1.28549419,"remaining_time":0.9937508281},
{"learn":[3.67075367],"iteration":564,"passed_time":1.287320174,"remaining_time":0.9911226115},
{"learn":[3.669765289],"iteration":565,"passed_time":1.289833083,"remaining_time":0.9890239541},
{"learn":[3.667896998],"iteration":566,"passed_time":1.298127929,"remaining_time":0.9913393179},
{"learn":[3.66398405],"iteration":567,"passed_time":1.299866274,"remaining_time":0.9886306874},
{"learn":[3.659379511],"iteration":568,"passed_time":1.301438634,"remaining_time":0.9857997388},
{"learn":[3.658807212],"iteration":569,"passed_time":1.303743762,"remaining_time":0.983525996},
{"learn":[3.657657996],"iteration":570,"passed_time":1.313420922,"remaining_time":0.9867908506},
{"learn":[3.656539512],"iteration":571,"passed_time":1.315493382,"remaining_time":0.984320223},
{"learn":[3.651563971],"iteration":572,"passed_time":1.318357663,"remaining_time":0.9824410507},
{"learn":[3.648330982],"iteration":573,"passed_time":1.320005823,"remaining_time":0.9796558897},
{"learn":[3.646313408],"iteration":574,"passed_time":1.325259552,"remaining_time":0.9795396689},
{"learn":[3.644566413],"iteration":575,"passed_time":1.332247831,"remaining_time":0.9806824309},
{"learn":[3.64358955],"iteration":576,"passed_time":1.33433857,"remaining_time":0.9782066118},
{"learn":[3.640937137],"iteration":577,"passed_time":1.343978203,"remaining_time":0.9812436017},
{"learn":[3.638672763],"iteration":578,"passed_time":1.346267565,"remaining_time":0.9788923051},
{"learn":[3.637520347],"iteration":579,"passed_time":1.350513994,"remaining_time":0.9779584094},
{"learn":[3.63559307],"iteration":580,"passed_time":1.357568123,"remaining_time":0.9790379409},
{"learn":[3.634058414],"iteration":581,"passed_time":1.359305869,"remaining_time":0.9762712255},
{"learn":[3.629351994],"iteration":582,"passed_time":1.362780848,"remaining_time":0.9747506235},
{"learn":[3.628158237],"iteration":583,"passed_time":1.365925631,"remaining_time":0.9729881207},
{"learn":[3.626108324],"iteration":584,"passed_time":1.37073009,"remaining_time":0.9723982689},
{"learn":[3.621090929],"iteration":585,"passed_time":1.372345865,"remaining_time":0.9695412768},
{"learn":[3.619618435],"iteration":586,"passed_time":1.373987329,"remaining_time":0.9667065877},
{"learn":[3.614857079],"iteration":587,"passed_time":1.377194951,"remaining_time":0.9649733329},
{"learn":[3.612395363],"iteration":588,"passed_time":1.379202316,"remaining_time":0.9623975411},
{"learn":[3.610968772],"iteration":589,"passed_time":1.385970817,"remaining_time":0.9631322629},
{"learn":[3.608848353],"iteration":590,"passed_time":1.387727506,"remaining_time":0.9603731809},
{"learn":[3.607611672],"iteration":591,"passed_time":1.389299311,"remaining_time":0.9574900654},
{"learn":[3.605932237],"iteration":592,"passed_time":1.390876905,"remaining_time":0.9546153462},
{"learn":[3.604121403],"iteration":593,"passed_time":1.395003027,"remaining_time":0.9534869176},
{"learn":[3.60203359],"iteration":594,"passed_time":1.399737554,"remaining_time":0.952762537},
{"learn":[3.599960233],"iteration":595,"passed_time":1.401685408,"remaining_time":0.9501357463},
{"learn":[3.597851149],"iteration":596,"passed_time":1.403413684,"remaining_time":0.9473630064},
{"learn":[3.593255289],"iteration":597,"passed_time":1.405081646,"remaining_time":0.9445532136},
{"learn":[3.591765394],"iteration":598,"passed_time":1.407320975,"remaining_time":0.9421297346},
{"learn":[3.591159733],"iteration":599,"passed_time":1.416102281,"remaining_time":0.944068187},
{"learn":[3.589622655],"iteration":600,"passed_time":1.418107407,"remaining_time":0.9414723054},
{"learn":[3.587518077],"iteration":601,"passed_time":1.419720455,"remaining_time":0.9386191709},
{"learn":[3.582764294],"iteration":602,"passed_time":1.421797326,"remaining_time":0.9360755197},
{"learn":[3.578956137],"iteration":603,"passed_time":1.429067244,"remaining_time":0.9369381268},
{"learn":[3.577402946],"iteration":604,"passed_time":1.431007244,"remaining_time":0.9342939856},
{"learn":[3.57693317],"iteration":605,"passed_time":1.433194826,"remaining_time":0.9318131374},
{"learn":[3.575421779],"iteration":606,"passed_time":1.434859915,"remaining_time":0.9289949699},
{"learn":[3.571741649],"iteration":607,"passed_time":1.438829275,"remaining_time":0.9276662432},
{"learn":[3.565107996],"iteration":608,"passed_time":1.443387744,"remaining_time":0.926707074},
{"learn":[3.56306319],"iteration":609,"passed_time":1.44513486,"remaining_time":0.9239386809},
{"learn":[3.561533405],"iteration":610,"passed_time":1.446785949,"remaining_time":0.9211124943},
{"learn":[3.560741836],"iteration":611,"passed_time":1.448458213,"remaining_time":0.9183035728},
{"learn":[3.560067725],"iteration":612,"passed_time":1.450962336,"remaining_time":0.9160235301},
{"learn":[3.558159868],"iteration":613,"passed_time":1.452775808,"remaining_time":0.9133085697},
{"learn":[3.557140575],"iteration":614,"passed_time":1.455044507,"remaining_time":0.9108815208},
{"learn":[3.556027881],"iteration":615,"passed_time":1.458133526,"remaining_time":0.9089663539},
{"learn":[3.553095867],"iteration":616,"passed_time":1.460710956,"remaining_time":0.9067298153},
{"learn":[3.550706617],"iteration":617,"passed_time":1.466370369,"remaining_time":0.9063972184},
{"learn":[3.548126974],"iteration":618,"passed_time":1.468435103,"remaining_time":0.9038348534},
{"learn":[3.546238663],"iteration":619,"passed_time":1.476856849,"remaining_time":0.9051703267},
{"learn":[3.543926194],"iteration":620,"passed_time":1.478575002,"remaining_time":0.9023831332},
{"learn":[3.541521881],"iteration":621,"passed_time":1.480490394,"remaining_time":0.8997192426},
{"learn":[3.540422253],"iteration":622,"passed_time":1.482175972,"remaining_time":0.8969186862},
{"learn":[3.53925803],"iteration":623,"passed_time":1.483942246,"remaining_time":0.8941703275},
{"learn":[3.536622339],"iteration":624,"passed_time":1.489443639,"remaining_time":0.8936661833},
{"learn":[3.532051288],"iteration":625,"passed_time":1.494037099,"remaining_time":0.8926036344},
{"learn":[3.531091626],"iteration":626,"passed_time":1.495791003,"remaining_time":0.8898405805},
{"learn":[3.529324769],"iteration":627,"passed_time":1.49758821,"remaining_time":0.8871063916},
{"learn":[3.526210552],"iteration":628,"passed_time":1.499357904,"remaining_time":0.8843589546},
{"learn":[3.52234166],"iteration":629,"passed_time":1.509709116,"remaining_time":0.8866545603},
{"learn":[3.518648544],"iteration":630,"passed_time":1.512251591,"remaining_time":0.8843436402},
{"learn":[3.515791241],"iteration":631,"passed_time":1.523851173,"remaining_time":0.8873057462},
{"learn":[3.514536901],"iteration":632,"passed_time":1.525999672,"remaining_time":0.8847423062},
{"learn":[3.511481186],"iteration":633,"passed_time":1.527604999,"remaining_time":0.8818666085},
{"learn":[3.507884796],"iteration":634,"passed_time":1.529333991,"remaining_time":0.879065995},
{"learn":[3.507041361],"iteration":635,"passed_time":1.53092739,"remaining_time":0.8761911477},
{"learn":[3.50433086],"iteration":636,"passed_time":1.539216051,"remaining_time":0.8771356771},
{"learn":[3.503055254],"iteration":637,"passed_time":1.541605076,"remaining_time":0.8747038206},
{"learn":[3.500877185],"iteration":638,"passed_time":1.544536423,"remaining_time":0.8725784799},
{"learn":[3.500331253],"iteration":639,"passed_time":1.546277669,"remaining_time":0.8697811891},
{"learn":[3.497333431],"iteration":640,"passed_time":1.552985518,"remaining_time":0.8697688},
{"learn":[3.495148044],"iteration":641,"passed_time":1.5550736,"remaining_time":0.8671594219},
{"learn":[3.49322115],"iteration":642,"passed_time":1.557461295,"remaining_time":0.8647180131},
{"learn":[3.492449516],"iteration":643,"passed_time":1.559947417,"remaining_time":0.8623311808},
{"learn":[3.491172903],"iteration":644,"passed_time":1.561640092,"remaining_time":0.8595073377},
{"learn":[3.490969433],"iteration":645,"passed_time":1.569238409,"remaining_time":0.8599232149},
{"learn":[3.489951287],"iteration":646,"passed_time":1.571716623,"remaining_time":0.8575208162},
{"learn":[3.487021633],"iteration":647,"passed_time":1.573597591,"remaining_time":0.854793753},
{"learn":[3.484206873],"iteration":648,"passed_time":1.575450632,"remaining_time":0.8520541937},
{"learn":[3.483372268],"iteration":649,"passed_time":1.577069927,"remaining_time":0.8491914993},
{"learn":[3.481263662],"iteration":650,"passed_time":1.583735847,"remaining_time":0.8490381113},
{"learn":[3.479269754],"iteration":651,"passed_time":1.586279208,"remaining_time":0.8466643627},
{"learn":[3.47741606],"iteration":652,"passed_time":1.588603827,"remaining_time":0.8441738559},
{"learn":[3.475676333],"iteration":653,"passed_time":1.590276701,"remaining_time":0.8413390498},
{"learn":[3.4743592],"iteration":654,"passed_time":1.591848241,"remaining_time":0.8384544169},
{"learn":[3.473039982],"iteration":655,"passed_time":1.601330113,"remaining_time":0.8397218883},
{"learn":[3.471144889],"iteration":656,"passed_time":1.603968177,"remaining_time":0.8373836903},
{"learn":[3.469695628],"iteration":657,"passed_time":1.60562366,"remaining_time":0.8345338781},
{"learn":[3.467554007],"iteration":658,"passed_time":1.60737598,"remaining_time":0.8317377985},
{"learn":[3.46577659],"iteration":659,"passed_time":1.609724297,"remaining_time":0.8292519107},
{"learn":[3.464330346],"iteration":660,"passed_time":1.614193119,"remaining_time":0.8278539595},
{"learn":[3.463816327],"iteration":661,"passed_time":1.619606079,"remaining_time":0.8269287836},
{"learn":[3.461150655],"iteration":662,"passed_time":1.621675676,"remaining_time":0.8242906528},
{"learn":[3.457745903],"iteration":663,"passed_time":1.623540668,"remaining_time":0.8215506993},
{"learn":[3.453740987],"iteration":664,"passed_time":1.629725052,"remaining_time":0.8209893121},
{"learn":[3.451297048],"iteration":665,"passed_time":1.631454252,"remaining_time":0.8181767572},
{"learn":[3.449926679],"iteration":666,"passed_time":1.634242662,"remaining_time":0.8158962617},
{"learn":[3.448552568],"iteration":667,"passed_time":1.636651278,"remaining_time":0.8134254853},
{"learn":[3.447574902],"iteration":668,"passed_time":1.638558775,"remaining_time":0.8107069575},
{"learn":[3.445570446],"iteration":669,"passed_time":1.641290349,"remaining_time":0.8083967391},
{"learn":[3.443962644],"iteration":670,"passed_time":1.646975068,"remaining_time":0.8075332301},
{"learn":[3.438846857],"iteration":671,"passed_time":1.64882332,"remaining_time":0.8047828112},
{"learn":[3.438081722],"iteration":672,"passed_time":1.650384372,"remaining_time":0.8018955269},
{"learn":[3.436980644],"iteration":673,"passed_time":1.652004768,"remaining_time":0.799040882},
{"learn":[3.436025995],"iteration":674,"passed_time":1.659229612,"remaining_time":0.7988883316},
{"learn":[3.435966142],"iteration":675,"passed_time":1.660889941,"remaining_time":0.7960478418},
{"learn":[3.435450254],"iteration":676,"passed_time":1.662484519,"remaining_time":0.7931794675},
{"learn":[3.434530188],"iteration":677,"passed_time":1.664135332,"remaining_time":0.7903415587},
{"learn":[3.433461656],"iteration":678,"passed_time":1.66580135,"remaining_time":0.7875143347},
{"learn":[3.431550434],"iteration":679,"passed_time":1.667776758,"remaining_time":0.7848361214},
{"learn":[3.429267293],"iteration":680,"passed_time":1.672870572,"remaining_time":0.7836207232},
{"learn":[3.42479327],"iteration":681,"passed_time":1.674783673,"remaining_time":0.7809108623},
{"learn":[3.422136465],"iteration":682,"passed_time":1.676237049,"remaining_time":0.7779899626},
{"learn":[3.420002782],"iteration":683,"passed_time":1.677671947,"remaining_time":0.7750648176},
{"learn":[3.416947799],"iteration":684,"passed_time":1.679123384,"remaining_time":0.772151629},
{"learn":[3.414905577],"iteration":685,"passed_time":1.680580509,"remaining_time":0.7692453059},
{"learn":[3.413439527],"iteration":686,"passed_time":1.681962929,"remaining_time":0.7663091656},
{"learn":[3.408316764],"iteration":687,"passed_time":1.683416988,"remaining_time":0.7634100295},
{"learn":[3.40657296],"iteration":688,"passed_time":1.688252122,"remaining_time":0.7620412338},
{"learn":[3.405112929],"iteration":689,"passed_time":1.689933163,"remaining_time":0.7592453342},
{"learn":[3.404312125],"iteration":690,"passed_time":1.691391619,"remaining_time":0.7563531264},
{"learn":[3.40098223],"iteration":691,"passed_time":1.69284091,"remaining_time":0.7534609831},
{"learn":[3.399879927],"iteration":692,"passed_time":1.694396874,"remaining_time":0.7506202601},
{"learn":[3.397764018],"iteration":693,"passed_time":1.695906875,"remaining_time":0.7477629738},
{"learn":[3.394762245],"iteration":694,"passed_time":1.697328212,"remaining_time":0.744870654},
{"learn":[3.392725269],"iteration":695,"passed_time":1.698917165,"remaining_time":0.7420557732},
{"learn":[3.392280551],"iteration":696,"passed_time":1.70224975,"remaining_time":0.7400024023},
{"learn":[3.390594185],"iteration":697,"passed_time":1.7040768,"remaining_time":0.7372939738},
{"learn":[3.389822931],"iteration":698,"passed_time":1.705740255,"remaining_time":0.7345176204},
{"learn":[3.388467872],"iteration":699,"passed_time":1.707406867,"remaining_time":0.7317458003},
{"learn":[3.386944906],"iteration":700,"passed_time":1.70910897,"remaining_time":0.728992271},
{"learn":[3.3864171],"iteration":701,"passed_time":1.710984345,"remaining_time":0.7263152916},
{"learn":[3.386170367],"iteration":702,"passed_time":1.712814142,"remaining_time":0.7236213372},
{"learn":[3.382612424],"iteration":703,"passed_time":1.715683745,"remaining_time":0.7213670292},
{"learn":[3.381274243],"iteration":704,"passed_time":1.71736829,"remaining_time":0.7186150999},
{"learn":[3.380575417],"iteration":705,"passed_time":1.718784071,"remaining_time":0.715754273},
{"learn":[3.378115312],"iteration":706,"passed_time":1.720312306,"remaining_time":0.712944138},
{"learn":[3.377854767],"iteration":707,"passed_time":1.721721881,"remaining_time":0.7100886853},
{"learn":[3.376067044],"iteration":708,"passed_time":1.723135297,"remaining_time":0.7072388877},
{"learn":[3.37427009],"iteration":709,"passed_time":1.724572078,"remaining_time":0.7044026797},
{"learn":[3.372096129],"iteration":710,"passed_time":1.726140725,"remaining_time":0.7016240077},
{"learn":[3.37063891],"iteration":711,"passed_time":1.727615463,"remaining_time":0.6988107492},
{"learn":[3.369685007],"iteration":712,"passed_time":1.729751256,"remaining_time":0.696267336},
{"learn":[3.368868468],"iteration":713,"passed_time":1.731648943,"remaining_time":0.6936296885},
{"learn":[3.367787859],"iteration":714,"passed_time":1.733171091,"remaining_time":0.690844421},
{"learn":[3.365195564],"iteration":715,"passed_time":1.734625503,"remaining_time":0.688035814},
{"learn":[3.364246158],"iteration":716,"passed_time":1.73602779,"remaining_time":0.685210411},
{"learn":[3.362585425],"iteration":717,"passed_time":1.737444115,"remaining_time":0.6823944852},
{"learn":[3.361541039],"iteration":718,"passed_time":1.739064355,"remaining_time":0.6796621472},
{"learn":[3.35968182],"iteration":719,"passed_time":1.740559159,"remaining_time":0.6768841175},
{"learn":[3.356706222],"iteration":720,"passed_time":1.741983222,"remaining_time":0.6740822731},
{"learn":[3.355738747],"iteration":721,"passed_time":1.743762622,"remaining_time":0.6714210649},
{"learn":[3.352943451],"iteration":722,"passed_time":1.746057654,"remaining_time":0.6689598482},
{"learn":[3.352054556],"iteration":723,"passed_time":1.747525254,"remaining_time":0.6661836605},
{"learn":[3.350764162],"iteration":724,"passed_time":1.7488876,"remaining_time":0.6633711585},
{"learn":[3.348147618],"iteration":725,"passed_time":1.75034255,"remaining_time":0.6605976014},
{"learn":[3.344679747],"iteration":726,"passed_time":1.751792486,"remaining_time":0.657825789},
{"learn":[3.341934917],"iteration":727,"passed_time":1.753423556,"remaining_time":0.6551252847},
{"learn":[3.339743597],"iteration":728,"passed_time":1.754885627,"remaining_time":0.6523648901},
{"learn":[3.339102981],"iteration":729,"passed_time":1.756318702,"remaining_time":0.6495973281},
{"learn":[3.337184999],"iteration":730,"passed_time":1.757756664,"remaining_time":0.6468352158},
{"learn":[3.334475496],"iteration":731,"passed_time":1.760694154,"remaining_time":0.6446257285},
{"learn":[3.330305514],"iteration":732,"passed_time":1.762213333,"remaining_time":0.641897626},
{"learn":[3.328707787],"iteration":733,"passed_time":1.763640365,"remaining_time":0.6391394238},
{"learn":[3.327220609],"iteration":734,"passed_time":1.7650866,"remaining_time":0.6363917674},
{"learn":[3.324740071],"iteration":735,"passed_time":1.76668575,"remaining_time":0.6337024972},
{"learn":[3.32398867],"iteration":736,"passed_time":1.768165879,"remaining_time":0.6309737126},
{"learn":[3.323087632],"iteration":737,"passed_time":1.769568968,"remaining_time":0.6282209614},
{"learn":[3.322369218],"iteration":738,"passed_time":1.770942501,"remaining_time":0.6254614247},
{"learn":[3.321257448],"iteration":739,"passed_time":1.772332582,"remaining_time":0.6227114478},
{"learn":[3.32054895],"iteration":740,"passed_time":1.77532005,"remaining_time":0.6205234723},
{"learn":[3.319794172],"iteration":741,"passed_time":1.776903638,"remaining_time":0.6178452004},
{"learn":[3.318754042],"iteration":742,"passed_time":1.778339539,"remaining_time":0.6151187909},
{"learn":[3.316641149],"iteration":743,"passed_time":1.779804699,"remaining_time":0.612405918},
{"learn":[3.315600852],"iteration":744,"passed_time":1.781584736,"remaining_time":0.6098041715},
{"learn":[3.314142669],"iteration":745,"passed_time":1.783455312,"remaining_time":0.6072354547},
{"learn":[3.312884073],"iteration":746,"passed_time":1.784948812,"remaining_time":0.6045408961},
{"learn":[3.309741305],"iteration":747,"passed_time":1.786376163,"remaining_time":0.6018272635},
{"learn":[3.307824509],"iteration":748,"passed_time":1.787838495,"remaining_time":0.5991287881},
{"learn":[3.307134844],"iteration":749,"passed_time":1.790670898,"remaining_time":0.5968902995},
{"learn":[3.30550535],"iteration":750,"passed_time":1.792619752,"remaining_time":0.5943572812},
{"learn":[3.303441953],"iteration":751,"passed_time":1.794193292,"remaining_time":0.5917020432},
{"learn":[3.299370477],"iteration":752,"passed_time":1.795781154,"remaining_time":0.5890543759},
{"learn":[3.298018725],"iteration":753,"passed_time":1.797308051,"remaining_time":0.5863896294},
{"learn":[3.295639908],"iteration":754,"passed_time":1.799280888,"remaining_time":0.5838726061},
{"learn":[3.292708721],"iteration":755,"passed_time":1.80127077,"remaining_time":0.5813625237},
{"learn":[3.290831934],"iteration":756,"passed_time":1.802886331,"remaining_time":0.5787336573},
{"learn":[3.289081337],"iteration":757,"passed_time":1.805917787,"remaining_time":0.5765595044},
{"learn":[3.287142259],"iteration":758,"passed_time":1.807402398,"remaining_time":0.5738919341},
{"learn":[3.284489323],"iteration":759,"passed_time":1.808876038,"remaining_time":0.5712240119},
{"learn":[3.282415058],"iteration":760,"passed_time":1.810295379,"remaining_time":0.5685421755},
{"learn":[3.281477943],"iteration":761,"passed_time":1.811707459,"remaining_time":0.5658613849},
{"learn":[3.277759064],"iteration":762,"passed_time":1.813143062,"remaining_time":0.5631912264},
{"learn":[3.276760294],"iteration":763,"passed_time":1.814705707,"remaining_time":0.5605635429},
{"learn":[3.275559773],"iteration":764,"passed_time":1.816120229,"remaining_time":0.5578931422},
{"learn":[3.273278215],"iteration":765,"passed_time":1.817532579,"remaining_time":0.555225357},
{"learn":[3.27175229],"iteration":766,"passed_time":1.820486731,"remaining_time":0.5530292157},
{"learn":[3.26828545],"iteration":767,"passed_time":1.822094519,"remaining_time":0.5504243861},
{"learn":[3.267769137],"iteration":768,"passed_time":1.823496575,"remaining_time":0.5477603497},
{"learn":[3.266772144],"iteration":769,"passed_time":1.824929291,"remaining_time":0.5451087493},
{"learn":[3.265363377],"iteration":770,"passed_time":1.8263268,"remaining_time":0.5424498536},
{"learn":[3.263827661],"iteration":771,"passed_time":1.827763986,"remaining_time":0.539805944},
{"learn":[3.259914731],"iteration":772,"passed_time":1.829473358,"remaining_time":0.537245087},
{"learn":[3.257668378],"iteration":773,"passed_time":1.831033774,"remaining_time":0.5346429367},
{"learn":[3.255931517],"iteration":774,"passed_time":1.832454515,"remaining_time":0.5320029236},
{"learn":[3.254557596],"iteration":775,"passed_time":1.835356409,"remaining_time":0.5297936026},
{"learn":[3.254030182],"iteration":776,"passed_time":1.836845616,"remaining_time":0.5271770557},
{"learn":[3.25234919],"iteration":777,"passed_time":1.838271555,"remaining_time":0.5245453539},
{"learn":[3.251942506],"iteration":778,"passed_time":1.839728925,"remaining_time":0.5219256641},
{"learn":[3.247791329],"iteration":779,"passed_time":1.841188958,"remaining_time":0.5193097062},
{"learn":[3.24738062],"iteration":780,"passed_time":1.842774302,"remaining_time":0.5167318464},
{"learn":[3.247093003],"iteration":781,"passed_time":1.84417021,"remaining_time":0.5141037157},
{"learn":[3.245904771],"iteration":782,"passed_time":1.845587498,"remaining_time":0.5114846579},
{"learn":[3.244713764],"iteration":783,"passed_time":1.846949013,"remaining_time":0.5088532995},
{"learn":[3.24312519],"iteration":784,"passed_time":1.849032328,"remaining_time":0.5064228669},
{"learn":[3.242525812],"iteration":785,"passed_time":1.850877833,"remaining_time":0.5039285704},
{"learn":[3.241646377],"iteration":786,"passed_time":1.852411305,"remaining_time":0.5013514714},
{"learn":[3.240472797],"iteration":787,"passed_time":1.853880395,"remaining_time":0.4987597002},
{"learn":[3.235847384],"iteration":788,"passed_time":1.855349946,"remaining_time":0.4961708982},
{"learn":[3.234645661],"iteration":789,"passed_time":1.857476646,"remaining_time":0.4937596148},
{"learn":[3.232819441],"iteration":790,"passed_time":1.859227354,"remaining_time":0.4912497054},
{"learn":[3.229530722],"iteration":791,"passed_time":1.860872074,"remaining_time":0.488713878},
{"learn":[3.228347952],"iteration":792,"passed_time":1.862411383,"remaining_time":0.4861527823},
{"learn":[3.226841612],"iteration":793,"passed_time":1.865482042,"remaining_time":0.4839915626},
{"learn":[3.225110454],"iteration":794,"passed_time":1.86734995,"remaining_time":0.4815179115},
{"learn":[3.22213953],"iteration":795,"passed_time":1.868824341,"remaining_time":0.4789449316},
{"learn":[3.22064099],"iteration":796,"passed_time":1.870542569,"remaining_time":0.4764368148},
{"learn":[3.21913822],"iteration":797,"passed_time":1.872200386,"remaining_time":0.4739153858},
{"learn":[3.217020644],"iteration":798,"passed_time":1.873771227,"remaining_time":0.4713742387},
{"learn":[3.210822518],"iteration":799,"passed_time":1.87529228,"remaining_time":0.4688230701},
{"learn":[3.208192356],"iteration":800,"passed_time":1.876775551,"remaining_time":0.466265087},
{"learn":[3.207555342],"iteration":801,"passed_time":1.88082104,"remaining_time":0.4643423516},
{"learn":[3.20689366],"iteration":802,"passed_time":1.882273199,"remaining_time":0.4617781074},
{"learn":[3.203564882],"iteration":803,"passed_time":1.883742684,"remaining_time":0.4592208533},
{"learn":[3.202092271],"iteration":804,"passed_time":1.88634036,"remaining_time":0.4569395903},
{"learn":[3.199222905],"iteration":805,"passed_time":1.889719442,"remaining_time":0.4548456225},
{"learn":[3.198002664],"iteration":806,"passed_time":1.892255376,"remaining_time":0.4525468248},
{"learn":[3.196311876],"iteration":807,"passed_time":1.895974662,"remaining_time":0.4505286326},
{"learn":[3.193763295],"iteration":808,"passed_time":1.897873205,"remaining_time":0.4480763685},
{"learn":[3.190823312],"iteration":809,"passed_time":1.89979354,"remaining_time":0.4456305835},
{"learn":[3.187116274],"iteration":810,"passed_time":1.901517976,"remaining_time":0.4431404407},
{"learn":[3.185874096],"iteration":811,"passed_time":1.903454013,"remaining_time":0.4407011754},
{"learn":[3.182625471],"iteration":812,"passed_time":1.905339092,"remaining_time":0.438251427},
{"learn":[3.182054705],"iteration":813,"passed_time":1.907086407,"remaining_time":0.4357715869},
{"learn":[3.180840205],"iteration":814,"passed_time":1.911230394,"remaining_time":0.4338375742},
{"learn":[3.178848067],"iteration":815,"passed_time":1.913032225,"remaining_time":0.4313700116},
{"learn":[3.177994928],"iteration":816,"passed_time":1.914464971,"remaining_time":0.4288214072},
{"learn":[3.176339077],"iteration":817,"passed_time":1.915967282,"remaining_time":0.4262910089},
{"learn":[3.175450121],"iteration":818,"passed_time":1.917471919,"remaining_time":0.4237636353},
{"learn":[3.173107991],"iteration":819,"passed_time":1.918926127,"remaining_time":0.4212276864},
{"learn":[3.170644507],"iteration":820,"passed_time":1.920445302,"remaining_time":0.4187085373},
{"learn":[3.170425292],"iteration":821,"passed_time":1.922241846,"remaining_time":0.4162518839},
{"learn":[3.169018701],"iteration":822,"passed_time":1.92414242,"remaining_time":0.4138192081},
{"learn":[3.16805069],"iteration":823,"passed_time":1.926690258,"remaining_time":0.4115260746},
{"learn":[3.166688888],"iteration":824,"passed_time":1.928167728,"remaining_time":0.4090052757},
{"learn":[3.165565216],"iteration":825,"passed_time":1.929580767,"remaining_time":0.4064734304},
{"learn":[3.163959449],"iteration":826,"passed_time":1.931053072,"remaining_time":0.4039566887},
{"learn":[3.162957083],"iteration":827,"passed_time":1.932973203,"remaining_time":0.4015354962},
{"learn":[3.160900183],"iteration":828,"passed_time":1.934442554,"remaining_time":0.3990225292},
{"learn":[3.159945183],"iteration":829,"passed_time":1.935816875,"remaining_time":0.3964926129},
{"learn":[3.159778774],"iteration":830,"passed_time":1.937167036,"remaining_time":0.3939605645},
{"learn":[3.159057626],"iteration":831,"passed_time":1.939016957,"remaining_time":0.3915322701},
{"learn":[3.15781515],"iteration":832,"passed_time":1.941608104,"remaining_time":0.3892539656},
{"learn":[3.155293032],"iteration":833,"passed_time":1.943448019,"remaining_time":0.3868253851},
{"learn":[3.154222921],"iteration":834,"passed_time":1.94497961,"remaining_time":0.3843372882},
{"learn":[3.153079639],"iteration":835,"passed_time":1.946429471,"remaining_time":0.3818354464},
{"learn":[3.151189476],"iteration":836,"passed_time":1.948193163,"remaining_time":0.3793972348},
{"learn":[3.150628829],"iteration":837,"passed_time":1.94968608,"remaining_time":0.3769082876},
{"learn":[3.150428875],"iteration":838,"passed_time":1.951139312,"remaining_time":0.3744140993},
{"learn":[3.149358559],"iteration":839,"passed_time":1.952559828,"remaining_time":0.3719161578},
{"learn":[3.148334781],"iteration":840,"passed_time":1.956427404,"remaining_time":0.3698834213},
{"learn":[3.147643531],"iteration":841,"passed_time":1.957964398,"remaining_time":0.3674089963},
{"learn":[3.145234306],"iteration":842,"passed_time":1.959437587,"remaining_time":0.3649249124},
{"learn":[3.144992166],"iteration":843,"passed_time":1.960825347,"remaining_time":0.3624274337},
{"learn":[3.14201588],"iteration":844,"passed_time":1.962372344,"remaining_time":0.3599617908},
{"learn":[3.141748388],"iteration":845,"passed_time":1.963762067,"remaining_time":0.3574696907},
{"learn":[3.139159864],"iteration":846,"passed_time":1.966022296,"remaining_time":0.3551374396},
{"learn":[3.135280251],"iteration":847,"passed_time":1.967860338,"remaining_time":0.3527296832},
{"learn":[3.133655013],"iteration":848,"passed_time":1.970799986,"remaining_time":0.3505191965},
{"learn":[3.132262592],"iteration":849,"passed_time":1.97293687,"remaining_time":0.34816533},
{"learn":[3.131091163],"iteration":850,"passed_time":1.974730415,"remaining_time":0.3457518588},
{"learn":[3.129817257],"iteration":851,"passed_time":1.976531637,"remaining_time":0.3433411764},
{"learn":[3.128642952],"iteration":852,"passed_time":1.978759574,"remaining_time":0.3410054601},
{"learn":[3.128039482],"iteration":853,"passed_time":1.980218919,"remaining_time":0.3385385974},
{"learn":[3.124544675],"iteration":854,"passed_time":1.981707037,"remaining_time":0.3360789712},
{"learn":[3.12396445],"iteration":855,"passed_time":1.983636092,"remaining_time":0.3336957911},
{"learn":[3.123288411],"iteration":856,"passed_time":1.986992242,"remaining_time":0.3315517976},
{"learn":[3.121769463],"iteration":857,"passed_time":1.988903288,"remaining_time":0.3291658122},
{"learn":[3.119711591],"iteration":858,"passed_time":1.990564688,"remaining_time":0.3267399547},
{"learn":[3.118785202],"iteration":859,"passed_time":1.992082839,"remaining_time":0.3242925553},
{"learn":[3.116449067],"iteration":860,"passed_time":1.993775088,"remaining_time":0.3218754207},
{"learn":[3.112816714],"iteration":861,"passed_time":1.99611798,"remaining_time":0.3195641313},
{"learn":[3.109547755],"iteration":862,"passed_time":1.998762174,"remaining_time":0.3173006001},
{"learn":[3.108202842],"iteration":863,"passed_time":2.001604327,"remaining_time":0.3150673477},
{"learn":[3.107169522],"iteration":864,"passed_time":2.003511529,"remaining_time":0.3126867704},
{"learn":[3.104891095],"iteration":865,"passed_time":2.005091254,"remaining_time":0.3102566143},
{"learn":[3.101202453],"iteration":866,"passed_time":2.006644783,"remaining_time":0.3078244016},
{"learn":[3.099398989],"iteration":867,"passed_time":2.009628072,"remaining_time":0.3056116423},
{"learn":[3.098092434],"iteration":868,"passed_time":2.011124044,"remaining_time":0.3031728996},
{"learn":[3.0955477],"iteration":869,"passed_time":2.012579725,"remaining_time":0.3007303037},
{"learn":[3.093128689],"iteration":870,"passed_time":2.015902345,"remaining_time":0.2985664782},
{"learn":[3.092355225],"iteration":871,"passed_time":2.019095852,"remaining_time":0.2963810425},
{"learn":[3.08970645],"iteration":872,"passed_time":2.020770408,"remaining_time":0.2939723273},
{"learn":[3.087349514],"iteration":873,"passed_time":2.022437958,"remaining_time":0.2915642822},
{"learn":[3.086415866],"iteration":874,"passed_time":2.02409711,"remaining_time":0.28915673},
{"learn":[3.084185568],"iteration":875,"passed_time":2.026368798,"remaining_time":0.2868375925},
{"learn":[3.08132989],"iteration":876,"passed_time":2.028129497,"remaining_time":0.2844468963},
{"learn":[3.080212469],"iteration":877,"passed_time":2.032745026,"remaining_time":0.2824543203},
{"learn":[3.079846152],"iteration":878,"passed_time":2.034647476,"remaining_time":0.2800823033},
{"learn":[3.078843206],"iteration":879,"passed_time":2.036323142,"remaining_time":0.2776804285},
{"learn":[3.078470666],"iteration":880,"passed_time":2.038014495,"remaining_time":0.2752823211},
{"learn":[3.077256218],"iteration":881,"passed_time":2.040781928,"remaining_time":0.2730297817},
{"learn":[3.07662157],"iteration":882,"passed_time":2.042707204,"remaining_time":0.2706644879},
{"learn":[3.076199276],"iteration":883,"passed_time":2.044621571,"remaining_time":0.2682987581},
{"learn":[3.073489584],"iteration":884,"passed_time":2.04721416,"remaining_time":0.266022179},
{"learn":[3.071208198],"iteration":885,"passed_time":2.048964601,"remaining_time":0.2636365288},
{"learn":[3.069388499],"iteration":886,"passed_time":2.050584965,"remaining_time":0.2612357396},
{"learn":[3.068587139],"iteration":887,"passed_time":2.052166061,"remaining_time":0.2588317554},
{"learn":[3.067771778],"iteration":888,"passed_time":2.054707667,"remaining_time":0.2565495512},
{"learn":[3.067190884],"iteration":889,"passed_time":2.056199371,"remaining_time":0.2541370009},
{"learn":[3.066401143],"iteration":890,"passed_time":2.057694463,"remaining_time":0.251726932},
{"learn":[3.065517675],"iteration":891,"passed_time":2.060374022,"remaining_time":0.2494623256},
{"learn":[3.063896529],"iteration":892,"passed_time":2.062382875,"remaining_time":0.2471164251},
{"learn":[3.063591299],"iteration":893,"passed_time":2.064038641,"remaining_time":0.2447294138},
{"learn":[3.06327084],"iteration":894,"passed_time":2.065878027,"remaining_time":0.2423655786},
{"learn":[3.062224641],"iteration":895,"passed_time":2.067633429,"remaining_time":0.2399931658},
{"learn":[3.060549185],"iteration":896,"passed_time":2.069560936,"remaining_time":0.2376418912},
{"learn":[3.058619383],"iteration":897,"passed_time":2.071361446,"remaining_time":0.2352771353},
{"learn":[3.056523822],"iteration":898,"passed_time":2.073042559,"remaining_time":0.2329002208},
{"learn":[3.055766057],"iteration":899,"passed_time":2.077353029,"remaining_time":0.2308170033},
{"learn":[3.055213266],"iteration":900,"passed_time":2.079014672,"remaining_time":0.2284377942},
{"learn":[3.053985696],"iteration":901,"passed_time":2.080734674,"remaining_time":0.2260665167},
{"learn":[3.051657383],"iteration":902,"passed_time":2.082215187,"remaining_time":0.2236709559},
{"learn":[3.050505053],"iteration":903,"passed_time":2.083657142,"remaining_time":0.2212733248},
{"learn":[3.049804048],"iteration":904,"passed_time":2.085091549,"remaining_time":0.2188770134},
{"learn":[3.048413334],"iteration":905,"passed_time":2.086557443,"remaining_time":0.2164860923},
{"learn":[3.047311293],"iteration":906,"passed_time":2.088019219,"remaining_time":0.2140967888},
{"learn":[3.043761899],"iteration":907,"passed_time":2.090923746,"remaining_time":0.2118557099},
{"learn":[3.043254364],"iteration":908,"passed_time":2.092861635,"remaining_time":0.2095164013},
{"learn":[3.041160462],"iteration":909,"passed_time":2.094540007,"remaining_time":0.2071523084},
{"learn":[3.04017728],"iteration":910,"passed_time":2.096098118,"remaining_time":0.204777972},
{"learn":[3.036412442],"iteration":911,"passed_time":2.097700412,"remaining_time":0.2024096889},
{"learn":[3.035246712],"iteration":912,"passed_time":2.099367349,"remaining_time":0.2000492435},
{"learn":[3.034759079],"iteration":913,"passed_time":2.101439372,"remaining_time":0.1977284311},
{"learn":[3.033825393],"iteration":914,"passed_time":2.105195741,"remaining_time":0.1955646317},
{"learn":[3.033116255],"iteration":915,"passed_time":2.106673679,"remaining_time":0.193188416},
{"learn":[3.032450366],"iteration":916,"passed_time":2.108173981,"remaining_time":0.1908161836},
{"learn":[3.030826388],"iteration":917,"passed_time":2.109629041,"remaining_time":0.1884418097},
{"learn":[3.029962711],"iteration":918,"passed_time":2.111073965,"remaining_time":0.1860685431},
{"learn":[3.025961553],"iteration":919,"passed_time":2.112687154,"remaining_time":0.1837119264},
{"learn":[3.025742648],"iteration":920,"passed_time":2.114111332,"remaining_time":0.1813407114},
{"learn":[3.024994987],"iteration":921,"passed_time":2.115495263,"remaining_time":0.1789681459},
{"learn":[3.024279294],"iteration":922,"passed_time":2.116928173,"remaining_time":0.1766018086},
{"learn":[3.022843677],"iteration":923,"passed_time":2.119689235,"remaining_time":0.1743467337},
{"learn":[3.022120242],"iteration":924,"passed_time":2.121157872,"remaining_time":0.1719857734},
{"learn":[3.018030405],"iteration":925,"passed_time":2.12257946,"remaining_time":0.1696229806},
{"learn":[3.017133658],"iteration":926,"passed_time":2.124006663,"remaining_time":0.1672626606},
{"learn":[3.016357279],"iteration":927,"passed_time":2.125379195,"remaining_time":0.16490011},
{"learn":[3.016171846],"iteration":928,"passed_time":2.126946703,"remaining_time":0.162554592},
{"learn":[3.015069188],"iteration":929,"passed_time":2.128366774,"remaining_time":0.1601996496},
{"learn":[3.014493903],"iteration":930,"passed_time":2.129799354,"remaining_time":0.1578476428},
{"learn":[3.012504244],"iteration":931,"passed_time":2.131232607,"remaining_time":0.155497658},
{"learn":[3.011069953],"iteration":932,"passed_time":2.134175012,"remaining_time":0.1532580127},
{"learn":[3.009848102],"iteration":933,"passed_time":2.135679569,"remaining_time":0.1509152586},
{"learn":[3.00842924],"iteration":934,"passed_time":2.137098968,"remaining_time":0.1485683775},
{"learn":[3.006518546],"iteration":935,"passed_time":2.1384959,"remaining_time":0.1462219419},
{"learn":[3.004750931],"iteration":936,"passed_time":2.139969559,"remaining_time":0.1438826918},
{"learn":[3.003207462],"iteration":937,"passed_time":2.141642702,"remaining_time":0.1415584728},
{"learn":[3.002545899],"iteration":938,"passed_time":2.143112849,"remaining_time":0.1392224534},
{"learn":[3.001639673],"iteration":939,"passed_time":2.144541229,"remaining_time":0.1368856104},
{"learn":[3.000671361],"iteration":940,"passed_time":2.145969993,"remaining_time":0.1345507222},
{"learn":[3.000236667],"iteration":941,"passed_time":2.148728962,"remaining_time":0.1322996601},
{"learn":[2.999539876],"iteration":942,"passed_time":2.150525878,"remaining_time":0.1299893691},
{"learn":[2.998678296],"iteration":943,"passed_time":2.151947924,"remaining_time":0.1276579277},
{"learn":[2.995839816],"iteration":944,"passed_time":2.153384684,"remaining_time":0.1253292673},
{"learn":[2.995090336],"iteration":945,"passed_time":2.155102001,"remaining_time":0.1230185074},
{"learn":[2.99210225],"iteration":946,"passed_time":2.156578361,"remaining_time":0.1206955154},
{"learn":[2.990287663],"iteration":947,"passed_time":2.158047093,"remaining_time":0.1183738912},
{"learn":[2.989788049],"iteration":948,"passed_time":2.159494803,"remaining_time":0.1160529346},
{"learn":[2.988745584],"iteration":949,"passed_time":2.161083975,"remaining_time":0.1137412619},
{"learn":[2.987665635],"iteration":950,"passed_time":2.16372639,"remaining_time":0.1114853766},
{"learn":[2.986051605],"iteration":951,"passed_time":2.165724611,"remaining_time":0.1091961989},
{"learn":[2.985972289],"iteration":952,"passed_time":2.167141879,"remaining_time":0.1068789804},
{"learn":[2.984044265],"iteration":953,"passed_time":2.169167117,"remaining_time":0.1045929637},
{"learn":[2.982161114],"iteration":954,"passed_time":2.170942439,"remaining_time":0.102295717},
{"learn":[2.982060255],"iteration":955,"passed_time":2.172411062,"remaining_time":0.09998544639},
{"learn":[2.980927593],"iteration":956,"passed_time":2.174092112,"remaining_time":0.09768647941},
{"learn":[2.979408915],"iteration":957,"passed_time":2.17582984,"remaining_time":0.09539128734},
{"learn":[2.977151839],"iteration":958,"passed_time":2.177702204,"remaining_time":0.09310301393},
{"learn":[2.977015338],"iteration":959,"passed_time":2.180786909,"remaining_time":0.09086612123},
{"learn":[2.974791438],"iteration":960,"passed_time":2.182561743,"remaining_time":0.08857430591},
{"learn":[2.97319523],"iteration":961,"passed_time":2.184148196,"remaining_time":0.08627612417},
{"learn":[2.972231035],"iteration":962,"passed_time":2.185755252,"remaining_time":0.08398021216},
{"learn":[2.970291269],"iteration":963,"passed_time":2.187362899,"remaining_time":0.08168575141},
{"learn":[2.969001762],"iteration":964,"passed_time":2.190705227,"remaining_time":0.07945563001},
{"learn":[2.967749979],"iteration":965,"passed_time":2.194377815,"remaining_time":0.07723482991},
{"learn":[2.965184926],"iteration":966,"passed_time":2.196458741,"remaining_time":0.07495670987},
{"learn":[2.964724912],"iteration":967,"passed_time":2.198397253,"remaining_time":0.07267428935},
{"learn":[2.964607579],"iteration":968,"passed_time":2.201017263,"remaining_time":0.07041438095},
{"learn":[2.963316326],"iteration":969,"passed_time":2.203381428,"remaining_time":0.06814581735},
{"learn":[2.961051484],"iteration":970,"passed_time":2.205212546,"remaining_time":0.06586113681},
{"learn":[2.961019466],"iteration":971,"passed_time":2.206574035,"remaining_time":0.0635638611},
{"learn":[2.958551471],"iteration":972,"passed_time":2.210842982,"remaining_time":0.06134918861},
{"learn":[2.955214769],"iteration":973,"passed_time":2.212997303,"remaining_time":0.05907384998},
{"learn":[2.955065089],"iteration":974,"passed_time":2.21466057,"remaining_time":0.05678616846},
{"learn":[2.954046988],"iteration":975,"passed_time":2.216295412,"remaining_time":0.0544990675},
{"learn":[2.952899234],"iteration":976,"passed_time":2.218173777,"remaining_time":0.05221903468},
{"learn":[2.95249511],"iteration":977,"passed_time":2.219869697,"remaining_time":0.04993571916},
{"learn":[2.952420606],"iteration":978,"passed_time":2.221435336,"remaining_time":0.04765080905},
{"learn":[2.949772333],"iteration":979,"passed_time":2.225599766,"remaining_time":0.04542040339},
{"learn":[2.94948274],"iteration":980,"passed_time":2.227263352,"remaining_time":0.04313761843},
{"learn":[2.94821817],"iteration":981,"passed_time":2.228846704,"remaining_time":0.04085462389},
{"learn":[2.947357128],"iteration":982,"passed_time":2.230375098,"remaining_time":0.03857210241},
{"learn":[2.946550947],"iteration":983,"passed_time":2.232151628,"remaining_time":0.03629514842},
{"learn":[2.944844749],"iteration":984,"passed_time":2.233653016,"remaining_time":0.03401502055},
{"learn":[2.943136142],"iteration":985,"passed_time":2.235248239,"remaining_time":0.03173780461},
{"learn":[2.941462776],"iteration":986,"passed_time":2.236783149,"remaining_time":0.02946117622},
{"learn":[2.938455907],"iteration":987,"passed_time":2.240663082,"remaining_time":0.02721453136},
{"learn":[2.937898489],"iteration":988,"passed_time":2.24220757,"remaining_time":0.02493860795},
{"learn":[2.936193928],"iteration":989,"passed_time":2.243795218,"remaining_time":0.02266459817},
{"learn":[2.932645414],"iteration":990,"passed_time":2.245556451,"remaining_time":0.02039355001},
{"learn":[2.930416476],"iteration":991,"passed_time":2.247310926,"remaining_time":0.01812347521},
{"learn":[2.929497758],"iteration":992,"passed_time":2.249075733,"remaining_time":0.01585451171},
{"learn":[2.9293797],"iteration":993,"passed_time":2.250703979,"remaining_time":0.01358573831},
{"learn":[2.927922682],"iteration":994,"passed_time":2.252292463,"remaining_time":0.01131805258},
{"learn":[2.927492577],"iteration":995,"passed_time":2.255984828,"remaining_time":0.009060180033},
{"learn":[2.926914829],"iteration":996,"passed_time":2.257520151,"remaining_time":0.00679293927},
{"learn":[2.924420059],"iteration":997,"passed_time":2.25921591,"remaining_time":0.004527486794},
{"learn":[2.922661086],"iteration":998,"passed_time":2.26089942,"remaining_time":0.002263162582},
{"learn":[2.922061239],"iteration":999,"passed_time":2.262498021,"remaining_time":0}
]}